{
"meta":{"test_sets":[],"test_metrics":[],"learn_metrics":[{"best_value":"Min","name":"Logloss"}],"launch_mode":"Train","parameters":"","iteration_count":1000,"learn_sets":["learn"],"name":"experiment"},
"iterations":[
{"learn":[0.6899352531],"iteration":0,"passed_time":0.02616482292,"remaining_time":26.1386581},
{"learn":[0.6868909159],"iteration":1,"passed_time":0.05212292729,"remaining_time":26.00934072},
{"learn":[0.6841609107],"iteration":2,"passed_time":0.07583620247,"remaining_time":25.20289796},
{"learn":[0.6816173573],"iteration":3,"passed_time":0.1011139714,"remaining_time":25.17737888},
{"learn":[0.6792401604],"iteration":4,"passed_time":0.117245933,"remaining_time":23.33194066},
{"learn":[0.677050021],"iteration":5,"passed_time":0.1414626076,"remaining_time":23.43563866},
{"learn":[0.6751596871],"iteration":6,"passed_time":0.162459211,"remaining_time":23.0459995},
{"learn":[0.6733435126],"iteration":7,"passed_time":0.1834618317,"remaining_time":22.74926714},
{"learn":[0.671650272],"iteration":8,"passed_time":0.2010833161,"remaining_time":22.14150737},
{"learn":[0.6701012879],"iteration":9,"passed_time":0.2289620678,"remaining_time":22.66724472},
{"learn":[0.6685522555],"iteration":10,"passed_time":0.2466727293,"remaining_time":22.17812084},
{"learn":[0.6673069382],"iteration":11,"passed_time":0.2594358523,"remaining_time":21.36021851},
{"learn":[0.666057486],"iteration":12,"passed_time":0.2729140006,"remaining_time":20.72047066},
{"learn":[0.6649476658],"iteration":13,"passed_time":0.2848100318,"remaining_time":20.05876367},
{"learn":[0.6638562927],"iteration":14,"passed_time":0.2968660483,"remaining_time":19.49420384},
{"learn":[0.6630450777],"iteration":15,"passed_time":0.3046088916,"remaining_time":18.73344683},
{"learn":[0.6620509275],"iteration":16,"passed_time":0.316644765,"remaining_time":18.30951788},
{"learn":[0.6611534631],"iteration":17,"passed_time":0.3293863833,"remaining_time":17.96985713},
{"learn":[0.6603824043],"iteration":18,"passed_time":0.3420186249,"remaining_time":17.65896164},
{"learn":[0.6596537924],"iteration":19,"passed_time":0.3526123491,"remaining_time":17.2780051},
{"learn":[0.6590134192],"iteration":20,"passed_time":0.3675281223,"remaining_time":17.13381104},
{"learn":[0.6583447318],"iteration":21,"passed_time":0.3825787324,"remaining_time":17.00736365},
{"learn":[0.657808276],"iteration":22,"passed_time":0.3948407763,"remaining_time":16.7721495},
{"learn":[0.6573106948],"iteration":23,"passed_time":0.4066555967,"remaining_time":16.5373276},
{"learn":[0.6567455247],"iteration":24,"passed_time":0.4183709064,"remaining_time":16.31646535},
{"learn":[0.6562309085],"iteration":25,"passed_time":0.4307278966,"remaining_time":16.13572966},
{"learn":[0.6558032728],"iteration":26,"passed_time":0.4429755061,"remaining_time":15.96352472},
{"learn":[0.6553913949],"iteration":27,"passed_time":0.4552140496,"remaining_time":15.80243058},
{"learn":[0.6549475117],"iteration":28,"passed_time":0.4680543863,"remaining_time":15.67175204},
{"learn":[0.6545293229],"iteration":29,"passed_time":0.480526436,"remaining_time":15.53702143},
{"learn":[0.6540972645],"iteration":30,"passed_time":0.4934973893,"remaining_time":15.42577323},
{"learn":[0.6537137108],"iteration":31,"passed_time":0.5072756249,"remaining_time":15.34508765},
{"learn":[0.6533614228],"iteration":32,"passed_time":0.5189168804,"remaining_time":15.20583707},
{"learn":[0.6530007237],"iteration":33,"passed_time":0.5316454886,"remaining_time":15.10498653},
{"learn":[0.652685217],"iteration":34,"passed_time":0.5435896169,"remaining_time":14.98754229},
{"learn":[0.6523265782],"iteration":35,"passed_time":0.5561037344,"remaining_time":14.89122222},
{"learn":[0.6520565066],"iteration":36,"passed_time":0.5685874809,"remaining_time":14.79864173},
{"learn":[0.6517559644],"iteration":37,"passed_time":0.5818116045,"remaining_time":14.72902009},
{"learn":[0.6513918449],"iteration":38,"passed_time":0.5942561755,"remaining_time":14.64308166},
{"learn":[0.6510789835],"iteration":39,"passed_time":0.6070896925,"remaining_time":14.57015262},
{"learn":[0.6508271886],"iteration":40,"passed_time":0.6179954102,"remaining_time":14.45506338},
{"learn":[0.6505821124],"iteration":41,"passed_time":0.6300053168,"remaining_time":14.37012127},
{"learn":[0.6503193662],"iteration":42,"passed_time":0.6424039227,"remaining_time":14.29722219},
{"learn":[0.6501176911],"iteration":43,"passed_time":0.6547734589,"remaining_time":14.22644152},
{"learn":[0.6499025498],"iteration":44,"passed_time":0.6657423753,"remaining_time":14.12853263},
{"learn":[0.6497072937],"iteration":45,"passed_time":0.6781833653,"remaining_time":14.06493327},
{"learn":[0.6494726423],"iteration":46,"passed_time":0.6906460716,"remaining_time":14.0039512},
{"learn":[0.6492729375],"iteration":47,"passed_time":0.7023221842,"remaining_time":13.92938999},
{"learn":[0.6490854168],"iteration":48,"passed_time":0.7145283919,"remaining_time":13.86768369},
{"learn":[0.6488779253],"iteration":49,"passed_time":0.7271209797,"remaining_time":13.81529861},
{"learn":[0.6487264876],"iteration":50,"passed_time":0.7390317649,"remaining_time":13.75178715},
{"learn":[0.6485239007],"iteration":51,"passed_time":0.7509038482,"remaining_time":13.68955477},
{"learn":[0.6483233156],"iteration":52,"passed_time":0.7620921388,"remaining_time":13.61700482},
{"learn":[0.6482063168],"iteration":53,"passed_time":0.7741007556,"remaining_time":13.56109842},
{"learn":[0.648022806],"iteration":54,"passed_time":0.7864661212,"remaining_time":13.5129179},
{"learn":[0.6477863675],"iteration":55,"passed_time":0.7980749157,"remaining_time":13.45326287},
{"learn":[0.6475741857],"iteration":56,"passed_time":0.810360794,"remaining_time":13.40649524},
{"learn":[0.6473987505],"iteration":57,"passed_time":0.8229784905,"remaining_time":13.36630583},
{"learn":[0.6471952893],"iteration":58,"passed_time":0.83618966,"remaining_time":13.33651644},
{"learn":[0.6469903643],"iteration":59,"passed_time":0.8473135438,"remaining_time":13.27457885},
{"learn":[0.6468693539],"iteration":60,"passed_time":0.8594928669,"remaining_time":13.23055413},
{"learn":[0.6467362479],"iteration":61,"passed_time":0.872009024,"remaining_time":13.19265265},
{"learn":[0.6465013833],"iteration":62,"passed_time":0.889002641,"remaining_time":13.22215039},
{"learn":[0.6463621177],"iteration":63,"passed_time":0.9039996057,"remaining_time":13.22099423},
{"learn":[0.6463037652],"iteration":64,"passed_time":0.9147414939,"remaining_time":13.15820457},
{"learn":[0.6461637904],"iteration":65,"passed_time":0.9269820714,"remaining_time":13.11820083},
{"learn":[0.6460204435],"iteration":66,"passed_time":0.9396214158,"remaining_time":13.08457882},
{"learn":[0.6458419568],"iteration":67,"passed_time":0.9515870374,"remaining_time":13.04233998},
{"learn":[0.6457457898],"iteration":68,"passed_time":0.9626637206,"remaining_time":12.9889844},
{"learn":[0.6455900281],"iteration":69,"passed_time":0.9756982321,"remaining_time":12.96284794},
{"learn":[0.645423554],"iteration":70,"passed_time":0.9879787156,"remaining_time":12.92721446},
{"learn":[0.6452831997],"iteration":71,"passed_time":0.9998110509,"remaining_time":12.88645355},
{"learn":[0.6451196191],"iteration":72,"passed_time":1.012091634,"remaining_time":12.85217732},
{"learn":[0.6449458649],"iteration":73,"passed_time":1.024455185,"remaining_time":12.8195338},
{"learn":[0.6448039746],"iteration":74,"passed_time":1.036601621,"remaining_time":12.78475333},
{"learn":[0.6445954746],"iteration":75,"passed_time":1.048964947,"remaining_time":12.75320541},
{"learn":[0.6444393381],"iteration":76,"passed_time":1.060683589,"remaining_time":12.71442796},
{"learn":[0.644264129],"iteration":77,"passed_time":1.073391763,"remaining_time":12.6880411},
{"learn":[0.6441211536],"iteration":78,"passed_time":1.085089448,"remaining_time":12.65022002},
{"learn":[0.6439992328],"iteration":79,"passed_time":1.096109614,"remaining_time":12.60526057},
{"learn":[0.6438722839],"iteration":80,"passed_time":1.108095255,"remaining_time":12.57209308},
{"learn":[0.643684216],"iteration":81,"passed_time":1.120857638,"remaining_time":12.54813795},
{"learn":[0.6435278621],"iteration":82,"passed_time":1.136857396,"remaining_time":12.56021966},
{"learn":[0.6433757509],"iteration":83,"passed_time":1.151117791,"remaining_time":12.55266544},
{"learn":[0.643246035],"iteration":84,"passed_time":1.168944188,"remaining_time":12.58334038},
{"learn":[0.6431365264],"iteration":85,"passed_time":1.181008058,"remaining_time":12.55164378},
{"learn":[0.6430382713],"iteration":86,"passed_time":1.193698319,"remaining_time":12.52697201},
{"learn":[0.6429050283],"iteration":87,"passed_time":1.20780951,"remaining_time":12.51729856},
{"learn":[0.6426798754],"iteration":88,"passed_time":1.229674486,"remaining_time":12.58689277},
{"learn":[0.642585988],"iteration":89,"passed_time":1.244759293,"remaining_time":12.58589952},
{"learn":[0.6424249442],"iteration":90,"passed_time":1.256435595,"remaining_time":12.55054896},
{"learn":[0.6422335247],"iteration":91,"passed_time":1.269217724,"remaining_time":12.52662711},
{"learn":[0.6420820592],"iteration":92,"passed_time":1.281293514,"remaining_time":12.4960561},
{"learn":[0.6420095297],"iteration":93,"passed_time":1.292346675,"remaining_time":12.45602221},
{"learn":[0.6418673333],"iteration":94,"passed_time":1.30442989,"remaining_time":12.42641105},
{"learn":[0.6417557066],"iteration":95,"passed_time":1.317130429,"remaining_time":12.40297821},
{"learn":[0.6415779284],"iteration":96,"passed_time":1.329953638,"remaining_time":12.38090861},
{"learn":[0.6414286399],"iteration":97,"passed_time":1.342001514,"remaining_time":12.35189149},
{"learn":[0.6412951365],"iteration":98,"passed_time":1.354407416,"remaining_time":12.32647557},
{"learn":[0.6411802396],"iteration":99,"passed_time":1.368042311,"remaining_time":12.3123808},
{"learn":[0.6411122486],"iteration":100,"passed_time":1.381622572,"remaining_time":12.29780884},
{"learn":[0.640994266],"iteration":101,"passed_time":1.396372874,"remaining_time":12.29355727},
{"learn":[0.6408557862],"iteration":102,"passed_time":1.407734483,"remaining_time":12.2595906},
{"learn":[0.6407246173],"iteration":103,"passed_time":1.420079114,"remaining_time":12.23452775},
{"learn":[0.6406312155],"iteration":104,"passed_time":1.431813641,"remaining_time":12.20450675},
{"learn":[0.6404981944],"iteration":105,"passed_time":1.443701267,"remaining_time":12.17612201},
{"learn":[0.6403543322],"iteration":106,"passed_time":1.45611707,"remaining_time":12.15245368},
{"learn":[0.6402903467],"iteration":107,"passed_time":1.467555168,"remaining_time":12.12091861},
{"learn":[0.640129491],"iteration":108,"passed_time":1.480895121,"remaining_time":12.10529865},
{"learn":[0.6400145681],"iteration":109,"passed_time":1.49279179,"remaining_time":12.07804267},
{"learn":[0.6399344427],"iteration":110,"passed_time":1.504175824,"remaining_time":12.04695772},
{"learn":[0.6398390864],"iteration":111,"passed_time":1.516626411,"remaining_time":12.02468083},
{"learn":[0.6396920553],"iteration":112,"passed_time":1.529511126,"remaining_time":12.00598556},
{"learn":[0.6395746513],"iteration":113,"passed_time":1.540599778,"remaining_time":11.97343336},
{"learn":[0.6394821092],"iteration":114,"passed_time":1.553847753,"remaining_time":11.95787184},
{"learn":[0.6393402485],"iteration":115,"passed_time":1.567858397,"remaining_time":11.94816227},
{"learn":[0.6392299544],"iteration":116,"passed_time":1.58070294,"remaining_time":11.9295786},
{"learn":[0.6391124438],"iteration":117,"passed_time":1.592631105,"remaining_time":11.90424266},
{"learn":[0.6389568429],"iteration":118,"passed_time":1.604000098,"remaining_time":11.87499232},
{"learn":[0.6388585791],"iteration":119,"passed_time":1.616240952,"remaining_time":11.85243365},
{"learn":[0.6387238564],"iteration":120,"passed_time":1.628528956,"remaining_time":11.83038803},
{"learn":[0.6386547882],"iteration":121,"passed_time":1.639383443,"remaining_time":11.79818576},
{"learn":[0.6384715961],"iteration":122,"passed_time":1.651941289,"remaining_time":11.7784757},
{"learn":[0.6382420577],"iteration":123,"passed_time":1.664998612,"remaining_time":11.76240955},
{"learn":[0.6381239789],"iteration":124,"passed_time":1.677731473,"remaining_time":11.74412031},
{"learn":[0.6380023082],"iteration":125,"passed_time":1.689004447,"remaining_time":11.71579275},
{"learn":[0.6379049122],"iteration":126,"passed_time":1.701091293,"remaining_time":11.69332833},
{"learn":[0.6378179628],"iteration":127,"passed_time":1.713397336,"remaining_time":11.67251935},
{"learn":[0.6376691812],"iteration":128,"passed_time":1.725310221,"remaining_time":11.64918762},
{"learn":[0.6375791326],"iteration":129,"passed_time":1.736879066,"remaining_time":11.62372913},
{"learn":[0.6374602282],"iteration":130,"passed_time":1.749543729,"remaining_time":11.60575191},
{"learn":[0.6373621207],"iteration":131,"passed_time":1.763012693,"remaining_time":11.59314407},
{"learn":[0.6372766195],"iteration":132,"passed_time":1.775659223,"remaining_time":11.575162},
{"learn":[0.6371863424],"iteration":133,"passed_time":1.786981316,"remaining_time":11.54870014},
{"learn":[0.6370939757],"iteration":134,"passed_time":1.798779037,"remaining_time":11.52551013},
{"learn":[0.6369840368],"iteration":135,"passed_time":1.811877043,"remaining_time":11.51074828},
{"learn":[0.6368404425],"iteration":136,"passed_time":1.824478673,"remaining_time":11.4928839},
{"learn":[0.636738748],"iteration":137,"passed_time":1.835531708,"remaining_time":11.4654227},
{"learn":[0.6366685427],"iteration":138,"passed_time":1.847427842,"remaining_time":11.44341994},
{"learn":[0.6365688231],"iteration":139,"passed_time":1.85992359,"remaining_time":11.42524491},
{"learn":[0.6364165035],"iteration":140,"passed_time":1.874371032,"remaining_time":11.41904054},
{"learn":[0.6363363673],"iteration":141,"passed_time":1.88890269,"remaining_time":11.41322893},
{"learn":[0.6362362561],"iteration":142,"passed_time":1.905419501,"remaining_time":11.41919239},
{"learn":[0.6361431808],"iteration":143,"passed_time":1.916988361,"remaining_time":11.39543081},
{"learn":[0.6360506431],"iteration":144,"passed_time":1.92904233,"remaining_time":11.37469788},
{"learn":[0.635980815],"iteration":145,"passed_time":1.952041932,"remaining_time":11.41810829},
{"learn":[0.6358346023],"iteration":146,"passed_time":1.965312268,"remaining_time":11.40415894},
{"learn":[0.6357657284],"iteration":147,"passed_time":1.976702399,"remaining_time":11.37939489},
{"learn":[0.6356378113],"iteration":148,"passed_time":1.98908088,"remaining_time":11.36045523},
{"learn":[0.6355454974],"iteration":149,"passed_time":2.001524373,"remaining_time":11.34197145},
{"learn":[0.6353728991],"iteration":150,"passed_time":2.014261247,"remaining_time":11.32521721},
{"learn":[0.6353074174],"iteration":151,"passed_time":2.026455127,"remaining_time":11.3054865},
{"learn":[0.6352338688],"iteration":152,"passed_time":2.037738053,"remaining_time":11.28081131},
{"learn":[0.6351521039],"iteration":153,"passed_time":2.04904167,"remaining_time":11.25642372},
{"learn":[0.6350556327],"iteration":154,"passed_time":2.061448537,"remaining_time":11.23821944},
{"learn":[0.634968727],"iteration":155,"passed_time":2.073444424,"remaining_time":11.21786598},
{"learn":[0.6348838879],"iteration":156,"passed_time":2.084808715,"remaining_time":11.19422769},
{"learn":[0.6348041418],"iteration":157,"passed_time":2.096904618,"remaining_time":11.1746436},
{"learn":[0.6347567977],"iteration":158,"passed_time":2.109822306,"remaining_time":11.15950038},
{"learn":[0.6346717482],"iteration":159,"passed_time":2.121984534,"remaining_time":11.1404188},
{"learn":[0.6345501092],"iteration":160,"passed_time":2.134131456,"remaining_time":11.12134342},
{"learn":[0.6344607293],"iteration":161,"passed_time":2.145872703,"remaining_time":11.10025509},
{"learn":[0.6343121934],"iteration":162,"passed_time":2.158521861,"remaining_time":11.08394354},
{"learn":[0.6342103107],"iteration":163,"passed_time":2.170606518,"remaining_time":11.06479908},
{"learn":[0.6340620341],"iteration":164,"passed_time":2.182445956,"remaining_time":11.04449923},
{"learn":[0.6339640163],"iteration":165,"passed_time":2.195234231,"remaining_time":11.02906837},
{"learn":[0.6338829718],"iteration":166,"passed_time":2.207988603,"remaining_time":11.01350004},
{"learn":[0.633768711],"iteration":167,"passed_time":2.221123918,"remaining_time":10.99985178},
{"learn":[0.6336782087],"iteration":168,"passed_time":2.232456194,"remaining_time":10.97734377},
{"learn":[0.633636952],"iteration":169,"passed_time":2.243861119,"remaining_time":10.95532193},
{"learn":[0.6334937471],"iteration":170,"passed_time":2.257454105,"remaining_time":10.94403189},
{"learn":[0.6333462389],"iteration":171,"passed_time":2.270090095,"remaining_time":10.92810813},
{"learn":[0.6332582632],"iteration":172,"passed_time":2.285455489,"remaining_time":10.92526988},
{"learn":[0.633128733],"iteration":173,"passed_time":2.297479504,"remaining_time":10.90642569},
{"learn":[0.6330426093],"iteration":174,"passed_time":2.310287741,"remaining_time":10.89135649},
{"learn":[0.6329492717],"iteration":175,"passed_time":2.322418217,"remaining_time":10.87313983},
{"learn":[0.6328255647],"iteration":176,"passed_time":2.334432746,"remaining_time":10.85445282},
{"learn":[0.632707269],"iteration":177,"passed_time":2.345581473,"remaining_time":10.83184253},
{"learn":[0.6325935881],"iteration":178,"passed_time":2.360362902,"remaining_time":10.82602203},
{"learn":[0.632520404],"iteration":179,"passed_time":2.372410328,"remaining_time":10.80764705},
{"learn":[0.6323927744],"iteration":180,"passed_time":2.385063261,"remaining_time":10.79208183},
{"learn":[0.6323178365],"iteration":181,"passed_time":2.395851949,"remaining_time":10.76816975},
{"learn":[0.6321911688],"iteration":182,"passed_time":2.408761065,"remaining_time":10.75386771},
{"learn":[0.6320866443],"iteration":183,"passed_time":2.420459423,"remaining_time":10.73421135},
{"learn":[0.632014054],"iteration":184,"passed_time":2.432689422,"remaining_time":10.71698313},
{"learn":[0.6319672161],"iteration":185,"passed_time":2.443758267,"remaining_time":10.69472704},
{"learn":[0.6318923857],"iteration":186,"passed_time":2.455980024,"remaining_time":10.67760299},
{"learn":[0.6317840097],"iteration":187,"passed_time":2.469033914,"remaining_time":10.6641252},
{"learn":[0.631650036],"iteration":188,"passed_time":2.481452468,"remaining_time":10.64792567},
{"learn":[0.6315779698],"iteration":189,"passed_time":2.492334844,"remaining_time":10.62521697},
{"learn":[0.6314978545],"iteration":190,"passed_time":2.504784073,"remaining_time":10.60926867},
{"learn":[0.6314436836],"iteration":191,"passed_time":2.516580603,"remaining_time":10.59061004},
{"learn":[0.6313578578],"iteration":192,"passed_time":2.529152521,"remaining_time":10.57526468},
{"learn":[0.6312928117],"iteration":193,"passed_time":2.541826357,"remaining_time":10.56037136},
{"learn":[0.6311915161],"iteration":194,"passed_time":2.553722193,"remaining_time":10.54228905},
{"learn":[0.6311285605],"iteration":195,"passed_time":2.56573886,"remaining_time":10.52476553},
{"learn":[0.6310030193],"iteration":196,"passed_time":2.577404713,"remaining_time":10.50586794},
{"learn":[0.6308941152],"iteration":197,"passed_time":2.588980024,"remaining_time":10.48667666},
{"learn":[0.6308149344],"iteration":198,"passed_time":2.601488358,"remaining_time":10.47131746},
{"learn":[0.630724424],"iteration":199,"passed_time":2.613758504,"remaining_time":10.45503402},
{"learn":[0.6305811681],"iteration":200,"passed_time":2.625173815,"remaining_time":10.43539243},
{"learn":[0.6304690443],"iteration":201,"passed_time":2.637196619,"remaining_time":10.41823219},
{"learn":[0.6303550869],"iteration":202,"passed_time":2.650881175,"remaining_time":10.40764678},
{"learn":[0.6302980177],"iteration":203,"passed_time":2.662589633,"remaining_time":10.38932033},
{"learn":[0.6301730078],"iteration":204,"passed_time":2.673973359,"remaining_time":10.36979913},
{"learn":[0.6300566247],"iteration":205,"passed_time":2.685972623,"remaining_time":10.35272943},
{"learn":[0.6299673327],"iteration":206,"passed_time":2.698450386,"remaining_time":10.33754182},
{"learn":[0.629898518],"iteration":207,"passed_time":2.709479816,"remaining_time":10.31686545},
{"learn":[0.6297496258],"iteration":208,"passed_time":2.721883244,"remaining_time":10.30148156},
{"learn":[0.6296920128],"iteration":209,"passed_time":2.733981219,"remaining_time":10.28497697},
{"learn":[0.6296190628],"iteration":210,"passed_time":2.747242064,"remaining_time":10.27286251},
{"learn":[0.6295535746],"iteration":211,"passed_time":2.759052575,"remaining_time":10.25534637},
{"learn":[0.6294621361],"iteration":212,"passed_time":2.770967234,"remaining_time":10.23826861},
{"learn":[0.629377133],"iteration":213,"passed_time":2.782729893,"remaining_time":10.22068082},
{"learn":[0.6292934912],"iteration":214,"passed_time":2.795837758,"remaining_time":10.20805879},
{"learn":[0.6291327966],"iteration":215,"passed_time":2.807775912,"remaining_time":10.19118664},
{"learn":[0.6290023163],"iteration":216,"passed_time":2.82167591,"remaining_time":10.18143888},
{"learn":[0.6288819229],"iteration":217,"passed_time":2.833870169,"remaining_time":10.16553427},
{"learn":[0.6288063633],"iteration":218,"passed_time":2.845938233,"remaining_time":10.14921352},
{"learn":[0.6287122118],"iteration":219,"passed_time":2.858343682,"remaining_time":10.1341276},
{"learn":[0.6285932634],"iteration":220,"passed_time":2.873809815,"remaining_time":10.12985451},
{"learn":[0.6284594374],"iteration":221,"passed_time":2.88634147,"remaining_time":10.11519668},
{"learn":[0.6283735526],"iteration":222,"passed_time":2.898254994,"remaining_time":10.09840417},
{"learn":[0.6283033278],"iteration":223,"passed_time":2.910186049,"remaining_time":10.08171595},
{"learn":[0.6281600558],"iteration":224,"passed_time":2.921451542,"remaining_time":10.06277753},
{"learn":[0.6280275685],"iteration":225,"passed_time":2.933375107,"remaining_time":10.04616077},
{"learn":[0.6278924898],"iteration":226,"passed_time":2.947760661,"remaining_time":10.03796912},
{"learn":[0.6277880364],"iteration":227,"passed_time":2.959823701,"remaining_time":10.0218592},
{"learn":[0.6277051653],"iteration":228,"passed_time":2.97090818,"remaining_time":10.00248999},
{"learn":[0.6276366066],"iteration":229,"passed_time":2.982933064,"remaining_time":9.986341128},
{"learn":[0.6274751538],"iteration":230,"passed_time":2.995936016,"remaining_time":9.973483968},
{"learn":[0.6273890055],"iteration":231,"passed_time":3.006653452,"remaining_time":9.953059702},
{"learn":[0.6272633072],"iteration":232,"passed_time":3.019076688,"remaining_time":9.938333989},
{"learn":[0.6271792169],"iteration":233,"passed_time":3.030552281,"remaining_time":9.920525845},
{"learn":[0.6270729566],"iteration":234,"passed_time":3.042380857,"remaining_time":9.903920663},
{"learn":[0.6269711754],"iteration":235,"passed_time":3.053371571,"remaining_time":9.884643561},
{"learn":[0.626846152],"iteration":236,"passed_time":3.065735634,"remaining_time":9.869857758},
{"learn":[0.6267774257],"iteration":237,"passed_time":3.076873293,"remaining_time":9.851165755},
{"learn":[0.6266524903],"iteration":238,"passed_time":3.088520773,"remaining_time":9.834160285},
{"learn":[0.6265572936],"iteration":239,"passed_time":3.100843282,"remaining_time":9.819337061},
{"learn":[0.6264787604],"iteration":240,"passed_time":3.113313946,"remaining_time":9.805001182},
{"learn":[0.6263677653],"iteration":241,"passed_time":3.12480911,"remaining_time":9.787625229},
{"learn":[0.6262453737],"iteration":242,"passed_time":3.136011933,"remaining_time":9.769386969},
{"learn":[0.626157747],"iteration":243,"passed_time":3.148224199,"remaining_time":9.754333995},
{"learn":[0.6260360663],"iteration":244,"passed_time":3.160519245,"remaining_time":9.739559306},
{"learn":[0.6259174641],"iteration":245,"passed_time":3.171874277,"remaining_time":9.721923597},
{"learn":[0.6258347655],"iteration":246,"passed_time":3.183883246,"remaining_time":9.706332324},
{"learn":[0.6256914789],"iteration":247,"passed_time":3.198228629,"remaining_time":9.697854551},
{"learn":[0.6255753401],"iteration":248,"passed_time":3.210077767,"remaining_time":9.681800816},
{"learn":[0.625462986],"iteration":249,"passed_time":3.22181052,"remaining_time":9.665431559},
{"learn":[0.6253450982],"iteration":250,"passed_time":3.233914962,"remaining_time":9.650208393},
{"learn":[0.6252526153],"iteration":251,"passed_time":3.246138429,"remaining_time":9.635363272},
{"learn":[0.6251632906],"iteration":252,"passed_time":3.25785167,"remaining_time":9.619032402},
{"learn":[0.6250626547],"iteration":253,"passed_time":3.269259196,"remaining_time":9.601840002},
{"learn":[0.6249594435],"iteration":254,"passed_time":3.280415452,"remaining_time":9.583958869},
{"learn":[0.6248087035],"iteration":255,"passed_time":3.292934263,"remaining_time":9.570090203},
{"learn":[0.6246666467],"iteration":256,"passed_time":3.305444356,"remaining_time":9.556206834},
{"learn":[0.6245485276],"iteration":257,"passed_time":3.316228955,"remaining_time":9.537371647},
{"learn":[0.6244307979],"iteration":258,"passed_time":3.329486987,"remaining_time":9.525675124},
{"learn":[0.6243509082],"iteration":259,"passed_time":3.341858646,"remaining_time":9.511443839},
{"learn":[0.6242696261],"iteration":260,"passed_time":3.354675683,"remaining_time":9.498487855},
{"learn":[0.6241398897],"iteration":261,"passed_time":3.366295076,"remaining_time":9.482159412},
{"learn":[0.6240292583],"iteration":262,"passed_time":3.377779803,"remaining_time":9.46548941},
{"learn":[0.6239289186],"iteration":263,"passed_time":3.389349003,"remaining_time":9.449094189},
{"learn":[0.6238245893],"iteration":264,"passed_time":3.40025392,"remaining_time":9.430892947},
{"learn":[0.6237445585],"iteration":265,"passed_time":3.413216125,"remaining_time":9.418423444},
{"learn":[0.6236437776],"iteration":266,"passed_time":3.424909251,"remaining_time":9.40246622},
{"learn":[0.6235447744],"iteration":267,"passed_time":3.43613358,"remaining_time":9.385260375},
{"learn":[0.6234293336],"iteration":268,"passed_time":3.448128932,"remaining_time":9.370194235},
{"learn":[0.6233068877],"iteration":269,"passed_time":3.460066463,"remaining_time":9.35499451},
{"learn":[0.6232225946],"iteration":270,"passed_time":3.471310052,"remaining_time":9.337952132},
{"learn":[0.6230983055],"iteration":271,"passed_time":3.482679966,"remaining_time":9.321290498},
{"learn":[0.6229919054],"iteration":272,"passed_time":3.495049304,"remaining_time":9.307329098},
{"learn":[0.6228391982],"iteration":273,"passed_time":3.508054907,"remaining_time":9.295065191},
{"learn":[0.6226886488],"iteration":274,"passed_time":3.521250072,"remaining_time":9.283295645},
{"learn":[0.6225931051],"iteration":275,"passed_time":3.532071028,"remaining_time":9.265287768},
{"learn":[0.6224884592],"iteration":276,"passed_time":3.544158845,"remaining_time":9.250638428},
{"learn":[0.6223859795],"iteration":277,"passed_time":3.556188617,"remaining_time":9.235856768},
{"learn":[0.6222826905],"iteration":278,"passed_time":3.567315186,"remaining_time":9.21876075},
{"learn":[0.6221529491],"iteration":279,"passed_time":3.578975782,"remaining_time":9.203080582},
{"learn":[0.6220140074],"iteration":280,"passed_time":3.591754846,"remaining_time":9.190290869},
{"learn":[0.6219279992],"iteration":281,"passed_time":3.60351458,"remaining_time":9.174905916},
{"learn":[0.6218293272],"iteration":282,"passed_time":3.614182965,"remaining_time":9.156781575},
{"learn":[0.6217288228],"iteration":283,"passed_time":3.627094565,"remaining_time":9.14436517},
{"learn":[0.6216418109],"iteration":284,"passed_time":3.638896582,"remaining_time":9.129161601},
{"learn":[0.6215563057],"iteration":285,"passed_time":3.650003301,"remaining_time":9.112246003},
{"learn":[0.6214346175],"iteration":286,"passed_time":3.662090061,"remaining_time":9.097805623},
{"learn":[0.621342724],"iteration":287,"passed_time":3.673712017,"remaining_time":9.082232487},
{"learn":[0.6212512077],"iteration":288,"passed_time":3.685820688,"remaining_time":9.067884115},
{"learn":[0.6211600213],"iteration":289,"passed_time":3.696321522,"remaining_time":9.049614761},
{"learn":[0.6210874758],"iteration":290,"passed_time":3.707735556,"remaining_time":9.033623742},
{"learn":[0.6210257334],"iteration":291,"passed_time":3.71884895,"remaining_time":9.016935124},
{"learn":[0.6208923493],"iteration":292,"passed_time":3.730231342,"remaining_time":9.000933648},
{"learn":[0.6207812289],"iteration":293,"passed_time":3.742754604,"remaining_time":8.987703232},
{"learn":[0.6206479378],"iteration":294,"passed_time":3.755283147,"remaining_time":8.974490233},
{"learn":[0.6205577039],"iteration":295,"passed_time":3.766477999,"remaining_time":8.958109835},
{"learn":[0.6204102825],"iteration":296,"passed_time":3.777707876,"remaining_time":8.941847263},
{"learn":[0.6203180456],"iteration":297,"passed_time":3.789528023,"remaining_time":8.927008968},
{"learn":[0.6202055621],"iteration":298,"passed_time":3.801172483,"remaining_time":8.911778966},
{"learn":[0.6201464748],"iteration":299,"passed_time":3.811758754,"remaining_time":8.89410376},
{"learn":[0.6200465289],"iteration":300,"passed_time":3.824150822,"remaining_time":8.880669184},
{"learn":[0.6199459418],"iteration":301,"passed_time":3.836002736,"remaining_time":8.865993079},
{"learn":[0.6198266823],"iteration":302,"passed_time":3.851568597,"remaining_time":8.859878917},
{"learn":[0.6197257292],"iteration":303,"passed_time":3.862334723,"remaining_time":8.842713708},
{"learn":[0.6195728779],"iteration":304,"passed_time":3.874643697,"remaining_time":8.82910613},
{"learn":[0.6194156019],"iteration":305,"passed_time":3.887559075,"remaining_time":8.816882347},
{"learn":[0.6193239085],"iteration":306,"passed_time":3.901980719,"remaining_time":8.808054195},
{"learn":[0.619205349],"iteration":307,"passed_time":3.913440333,"remaining_time":8.792534775},
{"learn":[0.619112762],"iteration":308,"passed_time":3.925063018,"remaining_time":8.777406297},
{"learn":[0.6189794153],"iteration":309,"passed_time":3.936896087,"remaining_time":8.76276871},
{"learn":[0.6189214822],"iteration":310,"passed_time":3.947617447,"remaining_time":8.745686241},
{"learn":[0.6188492961],"iteration":311,"passed_time":3.959618161,"remaining_time":8.731465689},
{"learn":[0.6187357171],"iteration":312,"passed_time":3.971619511,"remaining_time":8.717260716},
{"learn":[0.6186125771],"iteration":313,"passed_time":3.984294112,"remaining_time":8.704540639},
{"learn":[0.6185156158],"iteration":314,"passed_time":3.995922092,"remaining_time":8.689544867},
{"learn":[0.6183749563],"iteration":315,"passed_time":4.007805472,"remaining_time":8.675123236},
{"learn":[0.618288583],"iteration":316,"passed_time":4.019113307,"remaining_time":8.659477568},
{"learn":[0.6181811006],"iteration":317,"passed_time":4.032272897,"remaining_time":8.647830553},
{"learn":[0.6180979502],"iteration":318,"passed_time":4.042835573,"remaining_time":8.630630173},
{"learn":[0.618000596],"iteration":319,"passed_time":4.055266519,"remaining_time":8.617441352},
{"learn":[0.6178895213],"iteration":320,"passed_time":4.066950323,"remaining_time":8.602676852},
{"learn":[0.6178509315],"iteration":321,"passed_time":4.07714867,"remaining_time":8.584803722},
{"learn":[0.6177744583],"iteration":322,"passed_time":4.089939512,"remaining_time":8.572411919},
{"learn":[0.6176687802],"iteration":323,"passed_time":4.102484844,"remaining_time":8.559505415},
{"learn":[0.6175727185],"iteration":324,"passed_time":4.114111753,"remaining_time":8.544693641},
{"learn":[0.6174960341],"iteration":325,"passed_time":4.124853908,"remaining_time":8.52807219},
{"learn":[0.6174094811],"iteration":326,"passed_time":4.136984224,"remaining_time":8.514343677},
{"learn":[0.6173120025],"iteration":327,"passed_time":4.15682579,"remaining_time":8.51642357},
{"learn":[0.6172069382],"iteration":328,"passed_time":4.174033052,"remaining_time":8.512997502},
{"learn":[0.6171109296],"iteration":329,"passed_time":4.190117901,"remaining_time":8.507209072},
{"learn":[0.6169489261],"iteration":330,"passed_time":4.201877417,"remaining_time":8.492616289},
{"learn":[0.6167965164],"iteration":331,"passed_time":4.214420152,"remaining_time":8.47961645},
{"learn":[0.6166692662],"iteration":332,"passed_time":4.226356738,"remaining_time":8.465405238},
{"learn":[0.6165348317],"iteration":333,"passed_time":4.239309572,"remaining_time":8.453234057},
{"learn":[0.6164434927],"iteration":334,"passed_time":4.25097548,"remaining_time":8.438503566},
{"learn":[0.6163511798],"iteration":335,"passed_time":4.263339095,"remaining_time":8.425170116},
{"learn":[0.6162432706],"iteration":336,"passed_time":4.274601212,"remaining_time":8.409675382},
{"learn":[0.6161797731],"iteration":337,"passed_time":4.287568714,"remaining_time":8.397545825},
{"learn":[0.6160555302],"iteration":338,"passed_time":4.299638767,"remaining_time":8.383661431},
{"learn":[0.6159805054],"iteration":339,"passed_time":4.310703681,"remaining_time":8.367836557},
{"learn":[0.6158650033],"iteration":340,"passed_time":4.322062184,"remaining_time":8.352606977},
{"learn":[0.6157635881],"iteration":341,"passed_time":4.334196153,"remaining_time":8.338892014},
{"learn":[0.6156877294],"iteration":342,"passed_time":4.346137583,"remaining_time":8.324817469},
{"learn":[0.6155656669],"iteration":343,"passed_time":4.360424103,"remaining_time":8.315227359},
{"learn":[0.6154334494],"iteration":344,"passed_time":4.371512999,"remaining_time":8.299539172},
{"learn":[0.6153625191],"iteration":345,"passed_time":4.384282673,"remaining_time":8.287054532},
{"learn":[0.6152623471],"iteration":346,"passed_time":4.396421455,"remaining_time":8.273381008},
{"learn":[0.6151406429],"iteration":347,"passed_time":4.408400006,"remaining_time":8.259416104},
{"learn":[0.6150614012],"iteration":348,"passed_time":4.419478486,"remaining_time":8.243783652},
{"learn":[0.6150125842],"iteration":349,"passed_time":4.43068376,"remaining_time":8.228412698},
{"learn":[0.6149027362],"iteration":350,"passed_time":4.441440439,"remaining_time":8.212236026},
{"learn":[0.6148042694],"iteration":351,"passed_time":4.452346582,"remaining_time":8.196365298},
{"learn":[0.6147122762],"iteration":352,"passed_time":4.463878845,"remaining_time":8.181670292},
{"learn":[0.6146271632],"iteration":353,"passed_time":4.476875617,"remaining_time":8.169665673},
{"learn":[0.6144717812],"iteration":354,"passed_time":4.488744056,"remaining_time":8.155605398},
{"learn":[0.6143781918],"iteration":355,"passed_time":4.5009215,"remaining_time":8.142116421},
{"learn":[0.6143090875],"iteration":356,"passed_time":4.51175639,"remaining_time":8.126216691},
{"learn":[0.6142183202],"iteration":357,"passed_time":4.523287521,"remaining_time":8.111593822},
{"learn":[0.6141102445],"iteration":358,"passed_time":4.534674822,"remaining_time":8.096731368},
{"learn":[0.6140316807],"iteration":359,"passed_time":4.54676941,"remaining_time":8.083145618},
{"learn":[0.6139128888],"iteration":360,"passed_time":4.558583432,"remaining_time":8.069071505},
{"learn":[0.6138260974],"iteration":361,"passed_time":4.569558701,"remaining_time":8.053531633},
{"learn":[0.6137155813],"iteration":362,"passed_time":4.581613686,"remaining_time":8.03991162},
{"learn":[0.6136481049],"iteration":363,"passed_time":4.5933445,"remaining_time":8.025733796},
{"learn":[0.6135229386],"iteration":364,"passed_time":4.604032955,"remaining_time":8.009755963},
{"learn":[0.6134496986],"iteration":365,"passed_time":4.615979704,"remaining_time":7.995986701},
{"learn":[0.6133338502],"iteration":366,"passed_time":4.628398187,"remaining_time":7.983041015},
{"learn":[0.6132065122],"iteration":367,"passed_time":4.64086607,"remaining_time":7.970183033},
{"learn":[0.6131082657],"iteration":368,"passed_time":4.651618667,"remaining_time":7.95439398},
{"learn":[0.6129848831],"iteration":369,"passed_time":4.663145592,"remaining_time":7.939950603},
{"learn":[0.6129142677],"iteration":370,"passed_time":4.675574605,"remaining_time":7.927052363},
{"learn":[0.6128148449],"iteration":371,"passed_time":4.687421762,"remaining_time":7.913174372},
{"learn":[0.6127290847],"iteration":372,"passed_time":4.699530873,"remaining_time":7.899747607},
{"learn":[0.6126470501],"iteration":373,"passed_time":4.710593591,"remaining_time":7.884576439},
{"learn":[0.6125411819],"iteration":374,"passed_time":4.723887193,"remaining_time":7.873145321},
{"learn":[0.6124441182],"iteration":375,"passed_time":4.735785477,"remaining_time":7.859388663},
{"learn":[0.6123815479],"iteration":376,"passed_time":4.748171503,"remaining_time":7.846447868},
{"learn":[0.6122882828],"iteration":377,"passed_time":4.759652735,"remaining_time":7.832021167},
{"learn":[0.6121726585],"iteration":378,"passed_time":4.772672168,"remaining_time":7.820130386},
{"learn":[0.6120779462],"iteration":379,"passed_time":4.783507793,"remaining_time":7.80467061},
{"learn":[0.6119689973],"iteration":380,"passed_time":4.796093876,"remaining_time":7.792079026},
{"learn":[0.6118291263],"iteration":381,"passed_time":4.808529403,"remaining_time":7.779243904},
{"learn":[0.6117168661],"iteration":382,"passed_time":4.821028321,"remaining_time":7.766512986},
{"learn":[0.6116104642],"iteration":383,"passed_time":4.833180953,"remaining_time":7.753227778},
{"learn":[0.611467986],"iteration":384,"passed_time":4.848750974,"remaining_time":7.745407401},
{"learn":[0.6113898744],"iteration":385,"passed_time":4.860792551,"remaining_time":7.731934265},
{"learn":[0.6112630062],"iteration":386,"passed_time":4.874270489,"remaining_time":7.720743694},
{"learn":[0.6111705694],"iteration":387,"passed_time":4.885325119,"remaining_time":7.705719002},
{"learn":[0.6110555974],"iteration":388,"passed_time":4.896924687,"remaining_time":7.691570653},
{"learn":[0.6109276547],"iteration":389,"passed_time":4.909686085,"remaining_time":7.679252595},
{"learn":[0.6108027821],"iteration":390,"passed_time":4.922530874,"remaining_time":7.667062154},
{"learn":[0.6106767691],"iteration":391,"passed_time":4.934041019,"remaining_time":7.652798315},
{"learn":[0.6105487339],"iteration":392,"passed_time":4.94692596,"remaining_time":7.640671902},
{"learn":[0.6104214646],"iteration":393,"passed_time":4.959086103,"remaining_time":7.627426849},
{"learn":[0.6102695072],"iteration":394,"passed_time":4.971983969,"remaining_time":7.615317218},
{"learn":[0.6101569711],"iteration":395,"passed_time":4.983219375,"remaining_time":7.600667935},
{"learn":[0.6100431671],"iteration":396,"passed_time":4.995467085,"remaining_time":7.587573431},
{"learn":[0.6099616072],"iteration":397,"passed_time":5.007357444,"remaining_time":7.573942666},
{"learn":[0.6098522967],"iteration":398,"passed_time":5.019469318,"remaining_time":7.560654287},
{"learn":[0.6097197109],"iteration":399,"passed_time":5.030638339,"remaining_time":7.545957509},
{"learn":[0.6096435356],"iteration":400,"passed_time":5.042643055,"remaining_time":7.532526658},
{"learn":[0.6095107445],"iteration":401,"passed_time":5.054903671,"remaining_time":7.519483571},
{"learn":[0.6094312532],"iteration":402,"passed_time":5.067291144,"remaining_time":7.506632291},
{"learn":[0.6093340879],"iteration":403,"passed_time":5.078689124,"remaining_time":7.492323559},
{"learn":[0.6092842372],"iteration":404,"passed_time":5.090000783,"remaining_time":7.477902384},
{"learn":[0.6092095983],"iteration":405,"passed_time":5.104624174,"remaining_time":7.468341772},
{"learn":[0.6091167621],"iteration":406,"passed_time":5.117988453,"remaining_time":7.456921751},
{"learn":[0.6089904481],"iteration":407,"passed_time":5.130564419,"remaining_time":7.444348372},
{"learn":[0.6088879],"iteration":408,"passed_time":5.14316379,"remaining_time":7.431808801},
{"learn":[0.6088128463],"iteration":409,"passed_time":5.156240936,"remaining_time":7.419956469},
{"learn":[0.6087334784],"iteration":410,"passed_time":5.173658202,"remaining_time":7.414317959},
{"learn":[0.608649653],"iteration":411,"passed_time":5.192150818,"remaining_time":7.410156993},
{"learn":[0.6085867579],"iteration":412,"passed_time":5.203932817,"remaining_time":7.396388774},
{"learn":[0.6084645],"iteration":413,"passed_time":5.217007678,"remaining_time":7.384460143},
{"learn":[0.6083678853],"iteration":414,"passed_time":5.228589729,"remaining_time":7.370421666},
{"learn":[0.6083005198],"iteration":415,"passed_time":5.240307312,"remaining_time":7.356585265},
{"learn":[0.608263938],"iteration":416,"passed_time":5.251292108,"remaining_time":7.34173453},
{"learn":[0.6082164343],"iteration":417,"passed_time":5.262718922,"remaining_time":7.327517733},
{"learn":[0.6081589873],"iteration":418,"passed_time":5.275246309,"remaining_time":7.314840348},
{"learn":[0.6080441218],"iteration":419,"passed_time":5.287566378,"remaining_time":7.301877379},
{"learn":[0.6079710982],"iteration":420,"passed_time":5.299752142,"remaining_time":7.288732756},
{"learn":[0.6078790581],"iteration":421,"passed_time":5.311714822,"remaining_time":7.275287126},
{"learn":[0.607788759],"iteration":422,"passed_time":5.326140127,"remaining_time":7.265207691},
{"learn":[0.6077099755],"iteration":423,"passed_time":5.338032825,"remaining_time":7.251667233},
{"learn":[0.60757525],"iteration":424,"passed_time":5.349638171,"remaining_time":7.237745761},
{"learn":[0.6074462786],"iteration":425,"passed_time":5.361233146,"remaining_time":7.223821188},
{"learn":[0.6073796981],"iteration":426,"passed_time":5.373928374,"remaining_time":7.211383977},
{"learn":[0.6073005688],"iteration":427,"passed_time":5.386191161,"remaining_time":7.198367626},
{"learn":[0.6072350719],"iteration":428,"passed_time":5.397118576,"remaining_time":7.183577406},
{"learn":[0.607159513],"iteration":429,"passed_time":5.407564956,"remaining_time":7.1681675},
{"learn":[0.6070761301],"iteration":430,"passed_time":5.420138979,"remaining_time":7.155589511},
{"learn":[0.606986335],"iteration":431,"passed_time":5.433015961,"remaining_time":7.143409875},
{"learn":[0.6068787318],"iteration":432,"passed_time":5.444546776,"remaining_time":7.129464254},
{"learn":[0.6068072742],"iteration":433,"passed_time":5.456346588,"remaining_time":7.115880574},
{"learn":[0.6067114472],"iteration":434,"passed_time":5.468278705,"remaining_time":7.102476939},
{"learn":[0.6065933251],"iteration":435,"passed_time":5.4813577,"remaining_time":7.09056363},
{"learn":[0.6065054818],"iteration":436,"passed_time":5.492037985,"remaining_time":7.075554658},
{"learn":[0.6064267722],"iteration":437,"passed_time":5.503737194,"remaining_time":7.061872838},
{"learn":[0.6062931954],"iteration":438,"passed_time":5.51621244,"remaining_time":7.049191752},
{"learn":[0.6061610016],"iteration":439,"passed_time":5.527411773,"remaining_time":7.034887711},
{"learn":[0.6060552494],"iteration":440,"passed_time":5.538886241,"remaining_time":7.020946505},
{"learn":[0.6059998174],"iteration":441,"passed_time":5.550276405,"remaining_time":7.006910032},
{"learn":[0.6059065065],"iteration":442,"passed_time":5.562338024,"remaining_time":6.99372975},
{"learn":[0.6058021525],"iteration":443,"passed_time":5.573852567,"remaining_time":6.979869431},
{"learn":[0.6057267973],"iteration":444,"passed_time":5.58551916,"remaining_time":6.96620929},
{"learn":[0.6055928327],"iteration":445,"passed_time":5.598237345,"remaining_time":6.953864326},
{"learn":[0.6055237466],"iteration":446,"passed_time":5.608926579,"remaining_time":6.939007603},
{"learn":[0.6054368316],"iteration":447,"passed_time":5.621530085,"remaining_time":6.92652814},
{"learn":[0.6053510462],"iteration":448,"passed_time":5.63297877,"remaining_time":6.912630963},
{"learn":[0.6052649122],"iteration":449,"passed_time":5.645048484,"remaining_time":6.899503703},
{"learn":[0.6051520899],"iteration":450,"passed_time":5.656254498,"remaining_time":6.885329754},
{"learn":[0.6050496619],"iteration":451,"passed_time":5.669076396,"remaining_time":6.87312802},
{"learn":[0.6049713596],"iteration":452,"passed_time":5.681091395,"remaining_time":6.859949212},
{"learn":[0.6048602943],"iteration":453,"passed_time":5.692748458,"remaining_time":6.846345062},
{"learn":[0.6047452895],"iteration":454,"passed_time":5.705482708,"remaining_time":6.834039727},
{"learn":[0.6046569496],"iteration":455,"passed_time":5.71848763,"remaining_time":6.822055418},
{"learn":[0.6045441352],"iteration":456,"passed_time":5.730475817,"remaining_time":6.808858574},
{"learn":[0.6044729315],"iteration":457,"passed_time":5.741446121,"remaining_time":6.79446244},
{"learn":[0.6043635427],"iteration":458,"passed_time":5.753639687,"remaining_time":6.78152303},
{"learn":[0.6042666479],"iteration":459,"passed_time":5.766388479,"remaining_time":6.769238649},
{"learn":[0.6042021657],"iteration":460,"passed_time":5.778632889,"remaining_time":6.756362532},
{"learn":[0.6041090403],"iteration":461,"passed_time":5.789814465,"remaining_time":6.742251477},
{"learn":[0.6040257617],"iteration":462,"passed_time":5.801943839,"remaining_time":6.729252358},
{"learn":[0.6039524223],"iteration":463,"passed_time":5.814306377,"remaining_time":6.716526332},
{"learn":[0.6038849058],"iteration":464,"passed_time":5.827427089,"remaining_time":6.704674178},
{"learn":[0.6038056636],"iteration":465,"passed_time":5.838419629,"remaining_time":6.690377858},
{"learn":[0.6037396065],"iteration":466,"passed_time":5.850056389,"remaining_time":6.676830953},
{"learn":[0.6036264302],"iteration":467,"passed_time":5.862785423,"remaining_time":6.664533857},
{"learn":[0.6035617171],"iteration":468,"passed_time":5.873988655,"remaining_time":6.650507411},
{"learn":[0.603474758],"iteration":469,"passed_time":5.885086021,"remaining_time":6.636373599},
{"learn":[0.6033645123],"iteration":470,"passed_time":5.896603411,"remaining_time":6.622724425},
{"learn":[0.6033038617],"iteration":471,"passed_time":5.907737649,"remaining_time":6.608655675},
{"learn":[0.6032185625],"iteration":472,"passed_time":5.919940111,"remaining_time":6.59578951},
{"learn":[0.6031278611],"iteration":473,"passed_time":5.932051627,"remaining_time":6.582825223},
{"learn":[0.6030128735],"iteration":474,"passed_time":5.944113325,"remaining_time":6.569809464},
{"learn":[0.602950532],"iteration":475,"passed_time":5.955441112,"remaining_time":6.555989796},
{"learn":[0.6028823205],"iteration":476,"passed_time":5.967327062,"remaining_time":6.542792565},
{"learn":[0.6027855997],"iteration":477,"passed_time":5.979323825,"remaining_time":6.529721834},
{"learn":[0.6027024922],"iteration":478,"passed_time":5.991088881,"remaining_time":6.516403564},
{"learn":[0.6026071602],"iteration":479,"passed_time":6.002155953,"remaining_time":6.502335616},
{"learn":[0.6025012257],"iteration":480,"passed_time":6.014407019,"remaining_time":6.489557677},
{"learn":[0.6024483623],"iteration":481,"passed_time":6.02624055,"remaining_time":6.476333205},
{"learn":[0.6023524526],"iteration":482,"passed_time":6.037685449,"remaining_time":6.462698503},
{"learn":[0.6022699291],"iteration":483,"passed_time":6.049838478,"remaining_time":6.449827799},
{"learn":[0.6021618437],"iteration":484,"passed_time":6.061719938,"remaining_time":6.436671687},
{"learn":[0.6020966724],"iteration":485,"passed_time":6.073373501,"remaining_time":6.423279793},
{"learn":[0.6020123007],"iteration":486,"passed_time":6.084833343,"remaining_time":6.409690976},
{"learn":[0.6019123338],"iteration":487,"passed_time":6.097039152,"remaining_time":6.396893537},
{"learn":[0.601827762],"iteration":488,"passed_time":6.1096007,"remaining_time":6.384470261},
{"learn":[0.6017487847],"iteration":489,"passed_time":6.12034863,"remaining_time":6.370158778},
{"learn":[0.6016928922],"iteration":490,"passed_time":6.131646696,"remaining_time":6.356432114},
{"learn":[0.6015690924],"iteration":491,"passed_time":6.143983235,"remaining_time":6.343787568},
{"learn":[0.601506939],"iteration":492,"passed_time":6.156037919,"remaining_time":6.330854412},
{"learn":[0.6014576211],"iteration":493,"passed_time":6.168221157,"remaining_time":6.318056489},
{"learn":[0.6013786899],"iteration":494,"passed_time":6.18014911,"remaining_time":6.305000607},
{"learn":[0.6012947271],"iteration":495,"passed_time":6.191688523,"remaining_time":6.291554467},
{"learn":[0.6012232905],"iteration":496,"passed_time":6.203710636,"remaining_time":6.278604527},
{"learn":[0.6011198485],"iteration":497,"passed_time":6.215521475,"remaining_time":6.265445342},
{"learn":[0.6010626034],"iteration":498,"passed_time":6.227328775,"remaining_time":6.252288008},
{"learn":[0.6009963872],"iteration":499,"passed_time":6.23913669,"remaining_time":6.23913669},
{"learn":[0.6008662023],"iteration":500,"passed_time":6.250927061,"remaining_time":6.22597326},
{"learn":[0.6007710439],"iteration":501,"passed_time":6.263158185,"remaining_time":6.213252542},
{"learn":[0.6006924831],"iteration":502,"passed_time":6.27535069,"remaining_time":6.200495612},
{"learn":[0.6005836036],"iteration":503,"passed_time":6.286930834,"remaining_time":6.187138281},
{"learn":[0.6005324686],"iteration":504,"passed_time":6.297491289,"remaining_time":6.172788491},
{"learn":[0.6004306515],"iteration":505,"passed_time":6.310148164,"remaining_time":6.160500381},
{"learn":[0.6003453118],"iteration":506,"passed_time":6.322451143,"remaining_time":6.147866694},
{"learn":[0.6002848077],"iteration":507,"passed_time":6.335056313,"remaining_time":6.13552698},
{"learn":[0.6002212689],"iteration":508,"passed_time":6.345935119,"remaining_time":6.12152091},
{"learn":[0.6001696309],"iteration":509,"passed_time":6.358642768,"remaining_time":6.109284228},
{"learn":[0.6000672794],"iteration":510,"passed_time":6.371300379,"remaining_time":6.096997818},
{"learn":[0.6000123859],"iteration":511,"passed_time":6.381823112,"remaining_time":6.082675154},
{"learn":[0.5999388943],"iteration":512,"passed_time":6.394052242,"remaining_time":6.069987217},
{"learn":[0.5998498759],"iteration":513,"passed_time":6.405954114,"remaining_time":6.056991633},
{"learn":[0.5997731355],"iteration":514,"passed_time":6.417860094,"remaining_time":6.044004166},
{"learn":[0.5997099426],"iteration":515,"passed_time":6.429267244,"remaining_time":6.030552996},
{"learn":[0.5996497111],"iteration":516,"passed_time":6.44128898,"remaining_time":6.017683902},
{"learn":[0.5995632877],"iteration":517,"passed_time":6.45461724,"remaining_time":6.006033802},
{"learn":[0.5995132554],"iteration":518,"passed_time":6.46572914,"remaining_time":5.992323153},
{"learn":[0.5994077661],"iteration":519,"passed_time":6.479127429,"remaining_time":5.980733012},
{"learn":[0.5993248362],"iteration":520,"passed_time":6.490737369,"remaining_time":5.967491746},
{"learn":[0.5993033954],"iteration":521,"passed_time":6.502226475,"remaining_time":5.954146082},
{"learn":[0.5992168168],"iteration":522,"passed_time":6.512824033,"remaining_time":5.939994386},
{"learn":[0.5991205768],"iteration":523,"passed_time":6.524802348,"remaining_time":5.92711053},
{"learn":[0.5990401714],"iteration":524,"passed_time":6.536675684,"remaining_time":5.914135143},
{"learn":[0.5989817789],"iteration":525,"passed_time":6.546896269,"remaining_time":5.899674584},
{"learn":[0.5989261979],"iteration":526,"passed_time":6.558866811,"remaining_time":5.886800762},
{"learn":[0.5988578096],"iteration":527,"passed_time":6.571337298,"remaining_time":5.874377282},
{"learn":[0.5987705337],"iteration":528,"passed_time":6.58337133,"remaining_time":5.861565022},
{"learn":[0.5986764689],"iteration":529,"passed_time":6.594517456,"remaining_time":5.84796831},
{"learn":[0.5986113699],"iteration":530,"passed_time":6.606970576,"remaining_time":5.835535217},
{"learn":[0.5985306963],"iteration":531,"passed_time":6.618669272,"remaining_time":5.822438382},
{"learn":[0.5984247991],"iteration":532,"passed_time":6.629575138,"remaining_time":5.808652137},
{"learn":[0.5983415925],"iteration":533,"passed_time":6.640401996,"remaining_time":5.794807734},
{"learn":[0.598297088],"iteration":534,"passed_time":6.652404751,"remaining_time":5.781996653},
{"learn":[0.5982346102],"iteration":535,"passed_time":6.662877921,"remaining_time":5.767864469},
{"learn":[0.598153369],"iteration":536,"passed_time":6.67481966,"remaining_time":5.755012109},
{"learn":[0.5980913339],"iteration":537,"passed_time":6.686800165,"remaining_time":5.742196424},
{"learn":[0.5980133935],"iteration":538,"passed_time":6.699017913,"remaining_time":5.729586749},
{"learn":[0.5979014799],"iteration":539,"passed_time":6.710214527,"remaining_time":5.716108671},
{"learn":[0.5978294442],"iteration":540,"passed_time":6.722438204,"remaining_time":5.703510417},
{"learn":[0.5977185129],"iteration":541,"passed_time":6.73395321,"remaining_time":5.690314705},
{"learn":[0.597619465],"iteration":542,"passed_time":6.745040046,"remaining_time":5.676764827},
{"learn":[0.5975583359],"iteration":543,"passed_time":6.757214858,"remaining_time":5.664135984},
{"learn":[0.5974595363],"iteration":544,"passed_time":6.769244763,"remaining_time":5.651387829},
{"learn":[0.5973988667],"iteration":545,"passed_time":6.781373716,"remaining_time":5.638724665},
{"learn":[0.5973086526],"iteration":546,"passed_time":6.793969383,"remaining_time":5.626449964},
{"learn":[0.597237607],"iteration":547,"passed_time":6.806212707,"remaining_time":5.613883474},
{"learn":[0.5971358924],"iteration":548,"passed_time":6.819234198,"remaining_time":5.601957419},
{"learn":[0.5970276903],"iteration":549,"passed_time":6.833270596,"remaining_time":5.59085776},
{"learn":[0.5969070913],"iteration":550,"passed_time":6.844854239,"remaining_time":5.577748736},
{"learn":[0.5968178916],"iteration":551,"passed_time":6.857252348,"remaining_time":5.565306254},
{"learn":[0.5967882126],"iteration":552,"passed_time":6.868220045,"remaining_time":5.551707703},
{"learn":[0.5967259231],"iteration":553,"passed_time":6.87968357,"remaining_time":5.53851782},
{"learn":[0.5966159857],"iteration":554,"passed_time":6.890783564,"remaining_time":5.525042677},
{"learn":[0.5965213057],"iteration":555,"passed_time":6.904075436,"remaining_time":5.513326427},
{"learn":[0.5964686983],"iteration":556,"passed_time":6.916109056,"remaining_time":5.500603791},
{"learn":[0.596436134],"iteration":557,"passed_time":6.926386438,"remaining_time":5.486492484},
{"learn":[0.5963567123],"iteration":558,"passed_time":6.93764808,"remaining_time":5.473171384},
{"learn":[0.596306786],"iteration":559,"passed_time":6.949621453,"remaining_time":5.460416856},
{"learn":[0.5962456617],"iteration":560,"passed_time":6.960211653,"remaining_time":5.446582737},
{"learn":[0.5961554916],"iteration":561,"passed_time":6.971843169,"remaining_time":5.433571722},
{"learn":[0.5960500034],"iteration":562,"passed_time":6.983755363,"remaining_time":5.42078347},
{"learn":[0.5959654531],"iteration":563,"passed_time":6.995564368,"remaining_time":5.407918554},
{"learn":[0.5959009403],"iteration":564,"passed_time":7.008624762,"remaining_time":5.396020835},
{"learn":[0.5957857455],"iteration":565,"passed_time":7.020948007,"remaining_time":5.383553772},
{"learn":[0.5956708969],"iteration":566,"passed_time":7.032984764,"remaining_time":5.370868435},
{"learn":[0.5956007931],"iteration":567,"passed_time":7.044668197,"remaining_time":5.357916657},
{"learn":[0.5955177162],"iteration":568,"passed_time":7.055905515,"remaining_time":5.344631418},
{"learn":[0.5954282987],"iteration":569,"passed_time":7.067719163,"remaining_time":5.33178814},
{"learn":[0.5953545397],"iteration":570,"passed_time":7.079589326,"remaining_time":5.31899093},
{"learn":[0.5953090372],"iteration":571,"passed_time":7.091032021,"remaining_time":5.305877106},
{"learn":[0.5952134063],"iteration":572,"passed_time":7.103727494,"remaining_time":5.293702687},
{"learn":[0.5951496633],"iteration":573,"passed_time":7.116013328,"remaining_time":5.281222435},
{"learn":[0.5950765165],"iteration":574,"passed_time":7.127682176,"remaining_time":5.268286826},
{"learn":[0.5949906851],"iteration":575,"passed_time":7.139007428,"remaining_time":5.25510269},
{"learn":[0.5949126651],"iteration":576,"passed_time":7.150954908,"remaining_time":5.242381154},
{"learn":[0.5948438228],"iteration":577,"passed_time":7.163897324,"remaining_time":5.230388704},
{"learn":[0.5947889669],"iteration":578,"passed_time":7.177862854,"remaining_time":5.219136894},
{"learn":[0.5947463811],"iteration":579,"passed_time":7.194045876,"remaining_time":5.209481496},
{"learn":[0.5946506583],"iteration":580,"passed_time":7.207833078,"remaining_time":5.198075834},
{"learn":[0.5945635341],"iteration":581,"passed_time":7.220075836,"remaining_time":5.185552749},
{"learn":[0.5945065141],"iteration":582,"passed_time":7.232606182,"remaining_time":5.173236326},
{"learn":[0.5944005329],"iteration":583,"passed_time":7.24466757,"remaining_time":5.160585118},
{"learn":[0.5943050963],"iteration":584,"passed_time":7.25568148,"remaining_time":5.147192845},
{"learn":[0.5942079781],"iteration":585,"passed_time":7.26760525,"remaining_time":5.134451491},
{"learn":[0.5941346071],"iteration":586,"passed_time":7.279026729,"remaining_time":5.121359521},
{"learn":[0.5940626152],"iteration":587,"passed_time":7.289665415,"remaining_time":5.107724747},
{"learn":[0.5939520039],"iteration":588,"passed_time":7.301971483,"remaining_time":5.095263632},
{"learn":[0.5938934458],"iteration":589,"passed_time":7.314880803,"remaining_time":5.083222253},
{"learn":[0.5938105743],"iteration":590,"passed_time":7.327552289,"remaining_time":5.071013344},
{"learn":[0.5937493744],"iteration":591,"passed_time":7.339171666,"remaining_time":5.05807777},
{"learn":[0.5936592822],"iteration":592,"passed_time":7.352881091,"remaining_time":5.04658112},
{"learn":[0.5936077749],"iteration":593,"passed_time":7.364142464,"remaining_time":5.033403772},
{"learn":[0.5935423903],"iteration":594,"passed_time":7.375881659,"remaining_time":5.020558104},
{"learn":[0.593470298],"iteration":595,"passed_time":7.387049597,"remaining_time":5.007328921},
{"learn":[0.5934268761],"iteration":596,"passed_time":7.398847908,"remaining_time":4.994532173},
{"learn":[0.5933434213],"iteration":597,"passed_time":7.410895478,"remaining_time":4.981906324},
{"learn":[0.593274438],"iteration":598,"passed_time":7.422158757,"remaining_time":4.968757365},
{"learn":[0.5931890088],"iteration":599,"passed_time":7.434405989,"remaining_time":4.956270659},
{"learn":[0.5930889525],"iteration":600,"passed_time":7.447118499,"remaining_time":4.944093646},
{"learn":[0.593014153],"iteration":601,"passed_time":7.459335455,"remaining_time":4.931587228},
{"learn":[0.5929550993],"iteration":602,"passed_time":7.47021527,"remaining_time":4.91820143},
{"learn":[0.5928872761],"iteration":603,"passed_time":7.481881351,"remaining_time":4.905339429},
{"learn":[0.5927881912],"iteration":604,"passed_time":7.4943935,"remaining_time":4.893033773},
{"learn":[0.5927243],"iteration":605,"passed_time":7.506136395,"remaining_time":4.880227293},
{"learn":[0.5926924616],"iteration":606,"passed_time":7.516349105,"remaining_time":4.866433605},
{"learn":[0.5926063494],"iteration":607,"passed_time":7.528963974,"remaining_time":4.854200457},
{"learn":[0.5925174518],"iteration":608,"passed_time":7.541329631,"remaining_time":4.841806052},
{"learn":[0.5924292369],"iteration":609,"passed_time":7.552473048,"remaining_time":4.82863031},
{"learn":[0.592348513],"iteration":610,"passed_time":7.564431482,"remaining_time":4.815980109},
{"learn":[0.5922699207],"iteration":611,"passed_time":7.576287048,"remaining_time":4.803266952},
{"learn":[0.5922386853],"iteration":612,"passed_time":7.586880946,"remaining_time":4.789760075},
{"learn":[0.5922100845],"iteration":613,"passed_time":7.598144686,"remaining_time":4.776683793},
{"learn":[0.5921073651],"iteration":614,"passed_time":7.610562384,"remaining_time":4.764335801},
{"learn":[0.5920540874],"iteration":615,"passed_time":7.621524278,"remaining_time":4.75108007},
{"learn":[0.5919893606],"iteration":616,"passed_time":7.632875873,"remaining_time":4.738073678},
{"learn":[0.5919242816],"iteration":617,"passed_time":7.645288346,"remaining_time":4.725728395},
{"learn":[0.5918806812],"iteration":618,"passed_time":7.657192255,"remaining_time":4.713069869},
{"learn":[0.5917941958],"iteration":619,"passed_time":7.668804737,"remaining_time":4.700235161},
{"learn":[0.5917418164],"iteration":620,"passed_time":7.680664143,"remaining_time":4.687555089},
{"learn":[0.5917128201],"iteration":621,"passed_time":7.691830165,"remaining_time":4.674456274},
{"learn":[0.5916343929],"iteration":622,"passed_time":7.704220057,"remaining_time":4.662104272},
{"learn":[0.5915622436],"iteration":623,"passed_time":7.715558088,"remaining_time":4.649118335},
{"learn":[0.591484078],"iteration":624,"passed_time":7.727105943,"remaining_time":4.636263566},
{"learn":[0.5913812202],"iteration":625,"passed_time":7.740600991,"remaining_time":4.624576311},
{"learn":[0.5913099053],"iteration":626,"passed_time":7.751660476,"remaining_time":4.611434382},
{"learn":[0.5912541845],"iteration":627,"passed_time":7.763483064,"remaining_time":4.598751114},
{"learn":[0.5911364391],"iteration":628,"passed_time":7.776542592,"remaining_time":4.586800161},
{"learn":[0.5910527611],"iteration":629,"passed_time":7.78905809,"remaining_time":4.57452618},
{"learn":[0.5909745913],"iteration":630,"passed_time":7.800080186,"remaining_time":4.561378112},
{"learn":[0.5908600867],"iteration":631,"passed_time":7.814972815,"remaining_time":4.5504905},
{"learn":[0.5908035384],"iteration":632,"passed_time":7.827347305,"remaining_time":4.53813027},
{"learn":[0.5907511856],"iteration":633,"passed_time":7.840000992,"remaining_time":4.525931172},
{"learn":[0.5906984199],"iteration":634,"passed_time":7.850875229,"remaining_time":4.512707809},
{"learn":[0.5905988103],"iteration":635,"passed_time":7.862402426,"remaining_time":4.499865539},
{"learn":[0.5905358504],"iteration":636,"passed_time":7.874178272,"remaining_time":4.487169094},
{"learn":[0.5904360685],"iteration":637,"passed_time":7.887234568,"remaining_time":4.475202059},
{"learn":[0.5903714566],"iteration":638,"passed_time":7.898126501,"remaining_time":4.462008868},
{"learn":[0.5902885614],"iteration":639,"passed_time":7.909812677,"remaining_time":4.449269631},
{"learn":[0.5901614962],"iteration":640,"passed_time":7.922601948,"remaining_time":4.437151481},
{"learn":[0.5900565449],"iteration":641,"passed_time":7.935610903,"remaining_time":4.425153744},
{"learn":[0.5899838855],"iteration":642,"passed_time":7.946483871,"remaining_time":4.411966939},
{"learn":[0.5899153437],"iteration":643,"passed_time":7.958191153,"remaining_time":4.399248525},
{"learn":[0.5898294414],"iteration":644,"passed_time":7.970098597,"remaining_time":4.386643414},
{"learn":[0.5897502028],"iteration":645,"passed_time":7.981492198,"remaining_time":4.373758882},
{"learn":[0.5896480038],"iteration":646,"passed_time":7.995162809,"remaining_time":4.362121285},
{"learn":[0.5895876269],"iteration":647,"passed_time":8.006835808,"remaining_time":4.349392291},
{"learn":[0.5895286203],"iteration":648,"passed_time":8.017956242,"remaining_time":4.336367706},
{"learn":[0.5894160314],"iteration":649,"passed_time":8.029583323,"remaining_time":4.323621789},
{"learn":[0.5893251785],"iteration":650,"passed_time":8.041658679,"remaining_time":4.31111963},
{"learn":[0.5892703705],"iteration":651,"passed_time":8.053824733,"remaining_time":4.298667189},
{"learn":[0.5892057226],"iteration":652,"passed_time":8.065662298,"remaining_time":4.286041068},
{"learn":[0.5891128122],"iteration":653,"passed_time":8.077091678,"remaining_time":4.273201407},
{"learn":[0.589028278],"iteration":654,"passed_time":8.090183223,"remaining_time":4.261241545},
{"learn":[0.5889286218],"iteration":655,"passed_time":8.102498417,"remaining_time":4.248871121},
{"learn":[0.5888422644],"iteration":656,"passed_time":8.113269514,"remaining_time":4.235694739},
{"learn":[0.5887723481],"iteration":657,"passed_time":8.124796603,"remaining_time":4.222918599},
{"learn":[0.5886912604],"iteration":658,"passed_time":8.137306219,"remaining_time":4.21065466},
{"learn":[0.5886611243],"iteration":659,"passed_time":8.148585084,"remaining_time":4.197755952},
{"learn":[0.5885697893],"iteration":660,"passed_time":8.15924377,"remaining_time":4.184544082},
{"learn":[0.5885043373],"iteration":661,"passed_time":8.1711406,"remaining_time":4.171972089},
{"learn":[0.5884154381],"iteration":662,"passed_time":8.185070387,"remaining_time":4.160435476},
{"learn":[0.5882871938],"iteration":663,"passed_time":8.197304084,"remaining_time":4.148033392},
{"learn":[0.5882176158],"iteration":664,"passed_time":8.20787505,"remaining_time":4.134794198},
{"learn":[0.5881336413],"iteration":665,"passed_time":8.22048094,"remaining_time":4.122583535},
{"learn":[0.5880558395],"iteration":666,"passed_time":8.233739136,"remaining_time":4.11069735},
{"learn":[0.5880212642],"iteration":667,"passed_time":8.24442776,"remaining_time":4.097529964},
{"learn":[0.5879615441],"iteration":668,"passed_time":8.256279821,"remaining_time":4.084945621},
{"learn":[0.5878834306],"iteration":669,"passed_time":8.267945186,"remaining_time":4.072271509},
{"learn":[0.5878173721],"iteration":670,"passed_time":8.279609513,"remaining_time":4.059599895},
{"learn":[0.5877532205],"iteration":671,"passed_time":8.291271126,"remaining_time":4.046929954},
{"learn":[0.5876794548],"iteration":672,"passed_time":8.305721365,"remaining_time":4.035617959},
{"learn":[0.5875697094],"iteration":673,"passed_time":8.31776717,"remaining_time":4.023133676},
{"learn":[0.5875149952],"iteration":674,"passed_time":8.331751229,"remaining_time":4.011583925},
{"learn":[0.5874331005],"iteration":675,"passed_time":8.342948699,"remaining_time":3.998691388},
{"learn":[0.5873547604],"iteration":676,"passed_time":8.35509846,"remaining_time":3.986258202},
{"learn":[0.5872728135],"iteration":677,"passed_time":8.367240181,"remaining_time":3.973822033},
{"learn":[0.5872162287],"iteration":678,"passed_time":8.378970841,"remaining_time":3.9611924},
{"learn":[0.5871572572],"iteration":679,"passed_time":8.390967807,"remaining_time":3.948690733},
{"learn":[0.58710214],"iteration":680,"passed_time":8.402605029,"remaining_time":3.936022032},
{"learn":[0.5870371545],"iteration":681,"passed_time":8.414149072,"remaining_time":3.92331291},
{"learn":[0.5869497368],"iteration":682,"passed_time":8.425088965,"remaining_time":3.910326796},
{"learn":[0.5868927109],"iteration":683,"passed_time":8.437702255,"remaining_time":3.898119755},
{"learn":[0.5868279579],"iteration":684,"passed_time":8.449385478,"remaining_time":3.885483833},
{"learn":[0.586746407],"iteration":685,"passed_time":8.460797289,"remaining_time":3.872726456},
{"learn":[0.5867103222],"iteration":686,"passed_time":8.471313193,"remaining_time":3.859564817},
{"learn":[0.5866393121],"iteration":687,"passed_time":8.483190537,"remaining_time":3.847028267},
{"learn":[0.5865240271],"iteration":688,"passed_time":8.495335475,"remaining_time":3.834614416},
{"learn":[0.5864282135],"iteration":689,"passed_time":8.507185517,"remaining_time":3.822068856},
{"learn":[0.5863725321],"iteration":690,"passed_time":8.518690199,"remaining_time":3.80937087},
{"learn":[0.5862822739],"iteration":691,"passed_time":8.530698244,"remaining_time":3.796900375},
{"learn":[0.5862304144],"iteration":692,"passed_time":8.543207596,"remaining_time":3.784653293},
{"learn":[0.586140708],"iteration":693,"passed_time":8.554558546,"remaining_time":3.77189469},
{"learn":[0.5860865501],"iteration":694,"passed_time":8.566731983,"remaining_time":3.759501086},
{"learn":[0.5860308826],"iteration":695,"passed_time":8.578459519,"remaining_time":3.746913353},
{"learn":[0.5859835913],"iteration":696,"passed_time":8.589031703,"remaining_time":3.733825834},
{"learn":[0.5859148476],"iteration":697,"passed_time":8.601464339,"remaining_time":3.721550473},
{"learn":[0.5858643297],"iteration":698,"passed_time":8.612427831,"remaining_time":3.708642027},
{"learn":[0.5857987232],"iteration":699,"passed_time":8.623090764,"remaining_time":3.695610327},
{"learn":[0.5857299704],"iteration":700,"passed_time":8.635050757,"remaining_time":3.683138625},
{"learn":[0.5856298178],"iteration":701,"passed_time":8.648276186,"remaining_time":3.67120556},
{"learn":[0.5855364498],"iteration":702,"passed_time":8.660115322,"remaining_time":3.658683144},
{"learn":[0.5855030098],"iteration":703,"passed_time":8.670679747,"remaining_time":3.645626712},
{"learn":[0.5854246448],"iteration":704,"passed_time":8.682684507,"remaining_time":3.633180042},
{"learn":[0.5853598788],"iteration":705,"passed_time":8.69456402,"remaining_time":3.620682467},
{"learn":[0.5852947284],"iteration":706,"passed_time":8.705191901,"remaining_time":3.607667931},
{"learn":[0.5851979612],"iteration":707,"passed_time":8.717945596,"remaining_time":3.595536884},
{"learn":[0.5851361334],"iteration":708,"passed_time":8.730496151,"remaining_time":3.583320705},
{"learn":[0.5850646302],"iteration":709,"passed_time":8.742511739,"remaining_time":3.570885076},
{"learn":[0.58499371],"iteration":710,"passed_time":8.753301251,"remaining_time":3.557952266},
{"learn":[0.5849056807],"iteration":711,"passed_time":8.765987116,"remaining_time":3.545792541},
{"learn":[0.58483097],"iteration":712,"passed_time":8.77818072,"remaining_time":3.533433193},
{"learn":[0.5847828557],"iteration":713,"passed_time":8.790759081,"remaining_time":3.521228427},
{"learn":[0.5846827356],"iteration":714,"passed_time":8.801539576,"remaining_time":3.508305985},
{"learn":[0.584642974],"iteration":715,"passed_time":8.812203784,"remaining_time":3.4953434},
{"learn":[0.584574567],"iteration":716,"passed_time":8.82453334,"remaining_time":3.48304454},
{"learn":[0.5845284146],"iteration":717,"passed_time":8.835444297,"remaining_time":3.470188429},
{"learn":[0.5845006523],"iteration":718,"passed_time":8.846395169,"remaining_time":3.457353328},
{"learn":[0.5844267074],"iteration":719,"passed_time":8.8579147,"remaining_time":3.444744606},
{"learn":[0.5843280992],"iteration":720,"passed_time":8.872324284,"remaining_time":3.433257247},
{"learn":[0.5842675133],"iteration":721,"passed_time":8.883612564,"remaining_time":3.420559962},
{"learn":[0.5842469767],"iteration":722,"passed_time":8.894905761,"remaining_time":3.407868459},
{"learn":[0.5841827076],"iteration":723,"passed_time":8.906150795,"remaining_time":3.395162458},
{"learn":[0.5841209207],"iteration":724,"passed_time":8.916927137,"remaining_time":3.382282707},
{"learn":[0.5840743626],"iteration":725,"passed_time":8.928742745,"remaining_time":3.369800981},
{"learn":[0.5839967955],"iteration":726,"passed_time":8.94073011,"remaining_time":3.357385585},
{"learn":[0.5839388639],"iteration":727,"passed_time":8.951675106,"remaining_time":3.344581908},
{"learn":[0.5838440573],"iteration":728,"passed_time":8.963836351,"remaining_time":3.332235461},
{"learn":[0.5837703118],"iteration":729,"passed_time":8.978524285,"remaining_time":3.320824051},
{"learn":[0.5836934012],"iteration":730,"passed_time":8.990701844,"remaining_time":3.308479885},
{"learn":[0.5835997361],"iteration":731,"passed_time":9.001781716,"remaining_time":3.29573429},
{"learn":[0.5835170326],"iteration":732,"passed_time":9.013770591,"remaining_time":3.283324349},
{"learn":[0.5834344891],"iteration":733,"passed_time":9.025975534,"remaining_time":3.270993859},
{"learn":[0.5833865783],"iteration":734,"passed_time":9.037538818,"remaining_time":3.258432363},
{"learn":[0.5833378095],"iteration":735,"passed_time":9.048044863,"remaining_time":3.245494353},
{"learn":[0.5832721428],"iteration":736,"passed_time":9.059421061,"remaining_time":3.232873459},
{"learn":[0.5831522278],"iteration":737,"passed_time":9.07167191,"remaining_time":3.22056645},
{"learn":[0.5830622038],"iteration":738,"passed_time":9.082901015,"remaining_time":3.207898735},
{"learn":[0.5829915477],"iteration":739,"passed_time":9.096001018,"remaining_time":3.195892249},
{"learn":[0.5829481126],"iteration":740,"passed_time":9.107194251,"remaining_time":3.183216344},
{"learn":[0.5828586067],"iteration":741,"passed_time":9.118316104,"remaining_time":3.170519616},
{"learn":[0.5827577789],"iteration":742,"passed_time":9.131267439,"remaining_time":3.158459935},
{"learn":[0.5827179102],"iteration":743,"passed_time":9.142572544,"remaining_time":3.145831413},
{"learn":[0.5826497967],"iteration":744,"passed_time":9.154640072,"remaining_time":3.133467407},
{"learn":[0.5826080475],"iteration":745,"passed_time":9.16580258,"remaining_time":3.120796053},
{"learn":[0.5825309004],"iteration":746,"passed_time":9.178263789,"remaining_time":3.108568592},
{"learn":[0.5824584685],"iteration":747,"passed_time":9.190024918,"remaining_time":3.096104651},
{"learn":[0.5823947301],"iteration":748,"passed_time":9.201247619,"remaining_time":3.083462153},
{"learn":[0.5823101902],"iteration":749,"passed_time":9.212507944,"remaining_time":3.070835981},
{"learn":[0.5822507658],"iteration":750,"passed_time":9.224466429,"remaining_time":3.058444928},
{"learn":[0.5821423848],"iteration":751,"passed_time":9.237409127,"remaining_time":3.046379606},
{"learn":[0.5820482859],"iteration":752,"passed_time":9.248786222,"remaining_time":3.033798402},
{"learn":[0.581994738],"iteration":753,"passed_time":9.260539072,"remaining_time":3.021342986},
{"learn":[0.5819103529],"iteration":754,"passed_time":9.273415418,"remaining_time":3.00925401},
{"learn":[0.5818106823],"iteration":755,"passed_time":9.286021724,"remaining_time":2.997075794},
{"learn":[0.5817823984],"iteration":756,"passed_time":9.296658291,"remaining_time":2.984264154},
{"learn":[0.5816967573],"iteration":757,"passed_time":9.309069739,"remaining_time":2.972024903},
{"learn":[0.5815929915],"iteration":758,"passed_time":9.321509421,"remaining_time":2.959794164},
{"learn":[0.5815439731],"iteration":759,"passed_time":9.333608327,"remaining_time":2.947455261},
{"learn":[0.581466317],"iteration":760,"passed_time":9.345052455,"remaining_time":2.934911349},
{"learn":[0.5814065498],"iteration":761,"passed_time":9.356538982,"remaining_time":2.922383567},
{"learn":[0.5813436799],"iteration":762,"passed_time":9.369166541,"remaining_time":2.910212936},
{"learn":[0.5812870324],"iteration":763,"passed_time":9.379820237,"remaining_time":2.897431382},
{"learn":[0.5812408454],"iteration":764,"passed_time":9.391505376,"remaining_time":2.88497224},
{"learn":[0.5811698146],"iteration":765,"passed_time":9.403328313,"remaining_time":2.872557213},
{"learn":[0.5810939643],"iteration":766,"passed_time":9.414836671,"remaining_time":2.860048167},
{"learn":[0.5810427537],"iteration":767,"passed_time":9.426423712,"remaining_time":2.847565496},
{"learn":[0.5809720848],"iteration":768,"passed_time":9.438000721,"remaining_time":2.835082141},
{"learn":[0.5808635946],"iteration":769,"passed_time":9.44967587,"remaining_time":2.822630455},
{"learn":[0.5808045274],"iteration":770,"passed_time":9.460594967,"remaining_time":2.809956222},
{"learn":[0.5807284231],"iteration":771,"passed_time":9.47314237,"remaining_time":2.797767436},
{"learn":[0.5806657694],"iteration":772,"passed_time":9.485050883,"remaining_time":2.785390104},
{"learn":[0.5806335743],"iteration":773,"passed_time":9.495500234,"remaining_time":2.772587924},
{"learn":[0.5805851641],"iteration":774,"passed_time":9.50738342,"remaining_time":2.76020809},
{"learn":[0.5805088159],"iteration":775,"passed_time":9.520586193,"remaining_time":2.748210447},
{"learn":[0.5804439773],"iteration":776,"passed_time":9.531975045,"remaining_time":2.735689106},
{"learn":[0.5803844456],"iteration":777,"passed_time":9.5426529,"remaining_time":2.722967794},
{"learn":[0.580314858],"iteration":778,"passed_time":9.554759486,"remaining_time":2.710657056},
{"learn":[0.5802524486],"iteration":779,"passed_time":9.566952589,"remaining_time":2.698371243},
{"learn":[0.5801778925],"iteration":780,"passed_time":9.578430671,"remaining_time":2.685885169},
{"learn":[0.5800935689],"iteration":781,"passed_time":9.590324819,"remaining_time":2.673517661},
{"learn":[0.580005141],"iteration":782,"passed_time":9.602253565,"remaining_time":2.66116095},
{"learn":[0.5799156984],"iteration":783,"passed_time":9.614417297,"remaining_time":2.648870072},
{"learn":[0.5798573059],"iteration":784,"passed_time":9.628013166,"remaining_time":2.636971759},
{"learn":[0.5797767287],"iteration":785,"passed_time":9.640201026,"remaining_time":2.624685775},
{"learn":[0.5796952875],"iteration":786,"passed_time":9.651603927,"remaining_time":2.612187594},
{"learn":[0.5796287171],"iteration":787,"passed_time":9.663936427,"remaining_time":2.599942287},
{"learn":[0.5795691553],"iteration":788,"passed_time":9.675172846,"remaining_time":2.587403638},
{"learn":[0.5795058605],"iteration":789,"passed_time":9.687905993,"remaining_time":2.57526615},
{"learn":[0.5794599954],"iteration":790,"passed_time":9.699681607,"remaining_time":2.562874154},
{"learn":[0.5793715329],"iteration":791,"passed_time":9.71085376,"remaining_time":2.55032523},
{"learn":[0.5793307583],"iteration":792,"passed_time":9.722523494,"remaining_time":2.537909664},
{"learn":[0.5792441896],"iteration":793,"passed_time":9.734873809,"remaining_time":2.52567255},
{"learn":[0.5792084774],"iteration":794,"passed_time":9.746937898,"remaining_time":2.513361345},
{"learn":[0.5791355244],"iteration":795,"passed_time":9.757961028,"remaining_time":2.500783982},
{"learn":[0.579037782],"iteration":796,"passed_time":9.770983075,"remaining_time":2.488719654},
{"learn":[0.5789551397],"iteration":797,"passed_time":9.784442423,"remaining_time":2.476763621},
{"learn":[0.5788792798],"iteration":798,"passed_time":9.796827252,"remaining_time":2.464533514},
{"learn":[0.5787955258],"iteration":799,"passed_time":9.807931242,"remaining_time":2.45198281},
{"learn":[0.5787342609],"iteration":800,"passed_time":9.820538791,"remaining_time":2.439809263},
{"learn":[0.5786517977],"iteration":801,"passed_time":9.833325954,"remaining_time":2.427678976},
{"learn":[0.5785751547],"iteration":802,"passed_time":9.846262805,"remaining_time":2.415583777},
{"learn":[0.5784589159],"iteration":803,"passed_time":9.859240829,"remaining_time":2.403496521},
{"learn":[0.5783853283],"iteration":804,"passed_time":9.870446302,"remaining_time":2.390977676},
{"learn":[0.5782973822],"iteration":805,"passed_time":9.882255985,"remaining_time":2.37860752},
{"learn":[0.5782227282],"iteration":806,"passed_time":9.893916527,"remaining_time":2.366203085},
{"learn":[0.5781690613],"iteration":807,"passed_time":9.905053099,"remaining_time":2.353675984},
{"learn":[0.5781463587],"iteration":808,"passed_time":9.916366784,"remaining_time":2.341194136},
{"learn":[0.5780799933],"iteration":809,"passed_time":9.928814548,"remaining_time":2.32898119},
{"learn":[0.5780132323],"iteration":810,"passed_time":9.940874455,"remaining_time":2.316677278},
{"learn":[0.5779085706],"iteration":811,"passed_time":9.952981951,"remaining_time":2.304384984},
{"learn":[0.5778812361],"iteration":812,"passed_time":9.964392524,"remaining_time":2.291932844},
{"learn":[0.5778245215],"iteration":813,"passed_time":9.97634824,"remaining_time":2.279607829},
{"learn":[0.5777451316],"iteration":814,"passed_time":9.988109886,"remaining_time":2.267239667},
{"learn":[0.5776417033],"iteration":815,"passed_time":10.00168652,"remaining_time":2.255282256},
{"learn":[0.5775602805],"iteration":816,"passed_time":10.01462757,"remaining_time":2.243178513},
{"learn":[0.5774921523],"iteration":817,"passed_time":10.02659778,"remaining_time":2.230856719},
{"learn":[0.5774516429],"iteration":818,"passed_time":10.03764371,"remaining_time":2.218331517},
{"learn":[0.577343708],"iteration":819,"passed_time":10.05138949,"remaining_time":2.206402572},
{"learn":[0.5772441778],"iteration":820,"passed_time":10.07021115,"remaining_time":2.195575877},
{"learn":[0.5771702229],"iteration":821,"passed_time":10.09145946,"remaining_time":2.185255211},
{"learn":[0.5770853944],"iteration":822,"passed_time":10.11448117,"remaining_time":2.175289389},
{"learn":[0.5769938042],"iteration":823,"passed_time":10.12782129,"remaining_time":2.163223966},
{"learn":[0.5769000828],"iteration":824,"passed_time":10.1410699,"remaining_time":2.151136039},
{"learn":[0.5768087423],"iteration":825,"passed_time":10.16271164,"remaining_time":2.140813349},
{"learn":[0.5767323886],"iteration":826,"passed_time":10.18502332,"remaining_time":2.130603428},
{"learn":[0.5766812752],"iteration":827,"passed_time":10.20063316,"remaining_time":2.118972105},
{"learn":[0.5766109671],"iteration":828,"passed_time":10.21611386,"remaining_time":2.107304549},
{"learn":[0.5765538865],"iteration":829,"passed_time":10.229401,"remaining_time":2.095178517},
{"learn":[0.5765094933],"iteration":830,"passed_time":10.24114697,"remaining_time":2.082736267},
{"learn":[0.5764303922],"iteration":831,"passed_time":10.25227614,"remaining_time":2.070171143},
{"learn":[0.5763722223],"iteration":832,"passed_time":10.26443882,"remaining_time":2.057816666},
{"learn":[0.5763208897],"iteration":833,"passed_time":10.2769136,"remaining_time":2.04552477},
{"learn":[0.5762607056],"iteration":834,"passed_time":10.29144858,"remaining_time":2.033639539},
{"learn":[0.5761650566],"iteration":835,"passed_time":10.30308336,"remaining_time":2.021179031},
{"learn":[0.5761081906],"iteration":836,"passed_time":10.31530652,"remaining_time":2.008835082},
{"learn":[0.576072385],"iteration":837,"passed_time":10.32680826,"remaining_time":1.996351954},
{"learn":[0.5759991081],"iteration":838,"passed_time":10.33831645,"remaining_time":1.983872406},
{"learn":[0.5759429994],"iteration":839,"passed_time":10.34892517,"remaining_time":1.971223843},
{"learn":[0.575883386],"iteration":840,"passed_time":10.36148678,"remaining_time":1.958949343},
{"learn":[0.5757985927],"iteration":841,"passed_time":10.37360978,"remaining_time":1.946591859},
{"learn":[0.5757390614],"iteration":842,"passed_time":10.3846796,"remaining_time":1.934038787},
{"learn":[0.5756928829],"iteration":843,"passed_time":10.39670404,"remaining_time":1.921665676},
{"learn":[0.5756230468],"iteration":844,"passed_time":10.40871905,"remaining_time":1.90929166},
{"learn":[0.5755504041],"iteration":845,"passed_time":10.42094981,"remaining_time":1.896957766},
{"learn":[0.5754865405],"iteration":846,"passed_time":10.43207119,"remaining_time":1.884423721},
{"learn":[0.575404588],"iteration":847,"passed_time":10.44493619,"remaining_time":1.872205543},
{"learn":[0.5753801411],"iteration":848,"passed_time":10.45679466,"remaining_time":1.859806825},
{"learn":[0.5752645597],"iteration":849,"passed_time":10.46800048,"remaining_time":1.847294202},
{"learn":[0.5752328842],"iteration":850,"passed_time":10.4791902,"remaining_time":1.834781832},
{"learn":[0.5751552283],"iteration":851,"passed_time":10.49073005,"remaining_time":1.822333389},
{"learn":[0.5750946825],"iteration":852,"passed_time":10.50429966,"remaining_time":1.81023687},
{"learn":[0.5750715935],"iteration":853,"passed_time":10.51519302,"remaining_time":1.797679369},
{"learn":[0.5750044653],"iteration":854,"passed_time":10.52682604,"remaining_time":1.7852512},
{"learn":[0.5749407142],"iteration":855,"passed_time":10.53837245,"remaining_time":1.772810318},
{"learn":[0.5748523719],"iteration":856,"passed_time":10.54962513,"remaining_time":1.760322514},
{"learn":[0.5747899783],"iteration":857,"passed_time":10.56254844,"remaining_time":1.748114077},
{"learn":[0.5747138833],"iteration":858,"passed_time":10.57413756,"remaining_time":1.735684978},
{"learn":[0.5746403045],"iteration":859,"passed_time":10.58547145,"remaining_time":1.723216282},
{"learn":[0.5745750175],"iteration":860,"passed_time":10.5966114,"remaining_time":1.710718913},
{"learn":[0.5745244086],"iteration":861,"passed_time":10.60954618,"remaining_time":1.698512033},
{"learn":[0.5744606217],"iteration":862,"passed_time":10.62205892,"remaining_time":1.686236468},
{"learn":[0.5743881878],"iteration":863,"passed_time":10.63454926,"remaining_time":1.673956828},
{"learn":[0.5743022975],"iteration":864,"passed_time":10.64571828,"remaining_time":1.661470482},
{"learn":[0.5742472174],"iteration":865,"passed_time":10.65748267,"remaining_time":1.649079305},
{"learn":[0.5741737672],"iteration":866,"passed_time":10.66978616,"remaining_time":1.636772271},
{"learn":[0.5740608747],"iteration":867,"passed_time":10.68287203,"remaining_time":1.624584225},
{"learn":[0.5739501287],"iteration":868,"passed_time":10.69380664,"remaining_time":1.612069815},
{"learn":[0.5738560732],"iteration":869,"passed_time":10.7060723,"remaining_time":1.599757931},
{"learn":[0.5737991983],"iteration":870,"passed_time":10.71855567,"remaining_time":1.587478395},
{"learn":[0.5737419976],"iteration":871,"passed_time":10.72928863,"remaining_time":1.574941451},
{"learn":[0.5736162532],"iteration":872,"passed_time":10.74124795,"remaining_time":1.562587044},
{"learn":[0.5735530253],"iteration":873,"passed_time":10.7534345,"remaining_time":1.550266301},
{"learn":[0.5734706403],"iteration":874,"passed_time":10.7677181,"remaining_time":1.538245444},
{"learn":[0.5734365849],"iteration":875,"passed_time":10.77845793,"remaining_time":1.52571779},
{"learn":[0.5733784126],"iteration":876,"passed_time":10.78995437,"remaining_time":1.513300328},
{"learn":[0.5733434923],"iteration":877,"passed_time":10.80213327,"remaining_time":1.500979793},
{"learn":[0.5732460131],"iteration":878,"passed_time":10.81678096,"remaining_time":1.488999426},
{"learn":[0.5731891237],"iteration":879,"passed_time":10.83280015,"remaining_time":1.47720002},
{"learn":[0.5730865938],"iteration":880,"passed_time":10.84642275,"remaining_time":1.465067318},
{"learn":[0.5730373638],"iteration":881,"passed_time":10.86077189,"remaining_time":1.453028439},
{"learn":[0.5729656959],"iteration":882,"passed_time":10.87515063,"remaining_time":1.440988249},
{"learn":[0.5728989008],"iteration":883,"passed_time":10.88927213,"remaining_time":1.428909012},
{"learn":[0.5728591268],"iteration":884,"passed_time":10.90361534,"remaining_time":1.416853971},
{"learn":[0.5728050812],"iteration":885,"passed_time":10.91843468,"remaining_time":1.404855027},
{"learn":[0.5727392961],"iteration":886,"passed_time":10.93157532,"remaining_time":1.392635863},
{"learn":[0.5726872068],"iteration":887,"passed_time":10.94533137,"remaining_time":1.380492244},
{"learn":[0.572565951],"iteration":888,"passed_time":10.96060028,"remaining_time":1.368533894},
{"learn":[0.5724737955],"iteration":889,"passed_time":10.97455924,"remaining_time":1.356406198},
{"learn":[0.5724353952],"iteration":890,"passed_time":10.98818618,"remaining_time":1.344233775},
{"learn":[0.5723556935],"iteration":891,"passed_time":11.00305192,"remaining_time":1.332208079},
{"learn":[0.5722632742],"iteration":892,"passed_time":11.01735416,"remaining_time":1.320108506},
{"learn":[0.5722094532],"iteration":893,"passed_time":11.03118927,"remaining_time":1.307948615},
{"learn":[0.5721785418],"iteration":894,"passed_time":11.04440858,"remaining_time":1.295712738},
{"learn":[0.5720933382],"iteration":895,"passed_time":11.05915595,"remaining_time":1.28365203},
{"learn":[0.5720000812],"iteration":896,"passed_time":11.07320088,"remaining_time":1.271504671},
{"learn":[0.5719260523],"iteration":897,"passed_time":11.08692261,"remaining_time":1.259316377},
{"learn":[0.571880265],"iteration":898,"passed_time":11.10204954,"remaining_time":1.24728254},
{"learn":[0.5718255167],"iteration":899,"passed_time":11.11668312,"remaining_time":1.235187014},
{"learn":[0.5717549129],"iteration":900,"passed_time":11.1323001,"remaining_time":1.223193907},
{"learn":[0.5716803686],"iteration":901,"passed_time":11.14815226,"remaining_time":1.211218316},
{"learn":[0.5716191221],"iteration":902,"passed_time":11.1639111,"remaining_time":1.199224116},
{"learn":[0.5715643818],"iteration":903,"passed_time":11.17876462,"remaining_time":1.187125446},
{"learn":[0.5714997696],"iteration":904,"passed_time":11.19473932,"remaining_time":1.175138382},
{"learn":[0.57146109],"iteration":905,"passed_time":11.2081105,"remaining_time":1.162872392},
{"learn":[0.571373046],"iteration":906,"passed_time":11.22409129,"remaining_time":1.150871544},
{"learn":[0.5713014865],"iteration":907,"passed_time":11.23846024,"remaining_time":1.138698615},
{"learn":[0.5712737432],"iteration":908,"passed_time":11.2527906,"remaining_time":1.12651699},
{"learn":[0.5712510261],"iteration":909,"passed_time":11.27004432,"remaining_time":1.114619768},
{"learn":[0.5712045893],"iteration":910,"passed_time":11.28344758,"remaining_time":1.102334615},
{"learn":[0.5711495222],"iteration":911,"passed_time":11.29845186,"remaining_time":1.090201495},
{"learn":[0.5710926316],"iteration":912,"passed_time":11.31262148,"remaining_time":1.07798255},
{"learn":[0.5710266015],"iteration":913,"passed_time":11.3256203,"remaining_time":1.065649175},
{"learn":[0.5709377712],"iteration":914,"passed_time":11.33964049,"remaining_time":1.053409226},
{"learn":[0.5709003547],"iteration":915,"passed_time":11.35170508,"remaining_time":1.040986056},
{"learn":[0.5708579145],"iteration":916,"passed_time":11.3630472,"remaining_time":1.028498274},
{"learn":[0.5707585943],"iteration":917,"passed_time":11.3744045,"remaining_time":1.016014346},
{"learn":[0.5706694458],"iteration":918,"passed_time":11.3860032,"remaining_time":1.003554145},
{"learn":[0.5706051648],"iteration":919,"passed_time":11.39779873,"remaining_time":0.9911129333},
{"learn":[0.570550469],"iteration":920,"passed_time":11.40819351,"remaining_time":0.9785529721},
{"learn":[0.570496869],"iteration":921,"passed_time":11.41966992,"remaining_time":0.9660892121},
{"learn":[0.5703919177],"iteration":922,"passed_time":11.4319223,"remaining_time":0.9536923261},
{"learn":[0.5703030671],"iteration":923,"passed_time":11.44392217,"remaining_time":0.9412749835},
{"learn":[0.570234306],"iteration":924,"passed_time":11.45517936,"remaining_time":0.9287983266},
{"learn":[0.5701618973],"iteration":925,"passed_time":11.466878,"remaining_time":0.9163595808},
{"learn":[0.5701161281],"iteration":926,"passed_time":11.47865032,"remaining_time":0.9039282344},
{"learn":[0.570049462],"iteration":927,"passed_time":11.49146984,"remaining_time":0.8915795565},
{"learn":[0.5699885205],"iteration":928,"passed_time":11.50279048,"remaining_time":0.8791153109},
{"learn":[0.5698841255],"iteration":929,"passed_time":11.51492336,"remaining_time":0.8667146618},
{"learn":[0.5698048209],"iteration":930,"passed_time":11.52686977,"remaining_time":0.8543007673},
{"learn":[0.569770382],"iteration":931,"passed_time":11.53723847,"remaining_time":0.8417727637},
{"learn":[0.5697195686],"iteration":932,"passed_time":11.54884777,"remaining_time":0.8293384785},
{"learn":[0.569640233],"iteration":933,"passed_time":11.56076515,"remaining_time":0.8169277298},
{"learn":[0.5695365232],"iteration":934,"passed_time":11.57241453,"remaining_time":0.8044994057},
{"learn":[0.569453906],"iteration":935,"passed_time":11.58393472,"remaining_time":0.7920639127},
{"learn":[0.5693769153],"iteration":936,"passed_time":11.59644427,"remaining_time":0.7796968931},
{"learn":[0.5693259301],"iteration":937,"passed_time":11.60793555,"remaining_time":0.7672622645},
{"learn":[0.5692429363],"iteration":938,"passed_time":11.61881203,"remaining_time":0.7547897062},
{"learn":[0.5691866456],"iteration":939,"passed_time":11.6307163,"remaining_time":0.7423861465},
{"learn":[0.5691098365],"iteration":940,"passed_time":11.64283681,"remaining_time":0.729997207},
{"learn":[0.5690646947],"iteration":941,"passed_time":11.65370191,"remaining_time":0.7175315402},
{"learn":[0.5689988917],"iteration":942,"passed_time":11.66560562,"remaining_time":0.7051320468},
{"learn":[0.5689428973],"iteration":943,"passed_time":11.67665623,"remaining_time":0.6926829969},
{"learn":[0.5688723668],"iteration":944,"passed_time":11.68764869,"remaining_time":0.6802335215},
{"learn":[0.5688510743],"iteration":945,"passed_time":11.69886224,"remaining_time":0.6677997473},
{"learn":[0.5687578503],"iteration":946,"passed_time":11.71236732,"remaining_time":0.6554967982},
{"learn":[0.568701125],"iteration":947,"passed_time":11.72419002,"remaining_time":0.6430990305},
{"learn":[0.5686153651],"iteration":948,"passed_time":11.73506937,"remaining_time":0.6306517785},
{"learn":[0.5685167805],"iteration":949,"passed_time":11.7496414,"remaining_time":0.6184021788},
{"learn":[0.5684335787],"iteration":950,"passed_time":11.76215233,"remaining_time":0.6060414976},
{"learn":[0.5683914848],"iteration":951,"passed_time":11.77345432,"remaining_time":0.5936195455},
{"learn":[0.5683201887],"iteration":952,"passed_time":11.78478126,"remaining_time":0.5812011745},
{"learn":[0.5682823455],"iteration":953,"passed_time":11.79619046,"remaining_time":0.5687890579},
{"learn":[0.5682143096],"iteration":954,"passed_time":11.80870108,"remaining_time":0.5564309407},
{"learn":[0.568172035],"iteration":955,"passed_time":11.82110925,"remaining_time":0.5440677897},
{"learn":[0.568090489],"iteration":956,"passed_time":11.83304184,"remaining_time":0.5316831755},
{"learn":[0.5680650919],"iteration":957,"passed_time":11.84525401,"remaining_time":0.5193117626},
{"learn":[0.568000214],"iteration":958,"passed_time":11.85718042,"remaining_time":0.5069284643},
{"learn":[0.5679661094],"iteration":959,"passed_time":11.86733106,"remaining_time":0.4944721274},
{"learn":[0.5679085722],"iteration":960,"passed_time":11.87917386,"remaining_time":0.4820892617},
{"learn":[0.5678484141],"iteration":961,"passed_time":11.89098822,"remaining_time":0.4697063952},
{"learn":[0.5677865274],"iteration":962,"passed_time":11.90209925,"remaining_time":0.4572976868},
{"learn":[0.5676899478],"iteration":963,"passed_time":11.91364137,"remaining_time":0.4449077691},
{"learn":[0.5676183532],"iteration":964,"passed_time":11.92559688,"remaining_time":0.432534602},
{"learn":[0.5675473362],"iteration":965,"passed_time":11.93725278,"remaining_time":0.420151754},
{"learn":[0.5674679738],"iteration":966,"passed_time":11.94863723,"remaining_time":0.4077611464},
{"learn":[0.5674055483],"iteration":967,"passed_time":11.96107907,"remaining_time":0.3954075724},
{"learn":[0.5673143822],"iteration":968,"passed_time":11.97305598,"remaining_time":0.3830389425},
{"learn":[0.5672728299],"iteration":969,"passed_time":11.98394292,"remaining_time":0.3706374099},
{"learn":[0.567205297],"iteration":970,"passed_time":11.99616247,"remaining_time":0.3582787968},
{"learn":[0.5671129361],"iteration":971,"passed_time":12.00849407,"remaining_time":0.3459236976},
{"learn":[0.5670723481],"iteration":972,"passed_time":12.01982606,"remaining_time":0.3335409083},
{"learn":[0.5670096526],"iteration":973,"passed_time":12.03088317,"remaining_time":0.3211529389},
{"learn":[0.5669508718],"iteration":974,"passed_time":12.04286489,"remaining_time":0.3087914075},
{"learn":[0.5668994492],"iteration":975,"passed_time":12.05412636,"remaining_time":0.2964129432},
{"learn":[0.5668360361],"iteration":976,"passed_time":12.06533216,"remaining_time":0.2840354551},
{"learn":[0.5667262311],"iteration":977,"passed_time":12.07794835,"remaining_time":0.2716920897},
{"learn":[0.5666515777],"iteration":978,"passed_time":12.09012921,"remaining_time":0.2593388288},
{"learn":[0.5665872282],"iteration":979,"passed_time":12.10163429,"remaining_time":0.2469721284},
{"learn":[0.5665167989],"iteration":980,"passed_time":12.11327914,"remaining_time":0.2346098916},
{"learn":[0.5664825207],"iteration":981,"passed_time":12.12469306,"remaining_time":0.2222448829},
{"learn":[0.5664220858],"iteration":982,"passed_time":12.13787144,"remaining_time":0.2099123241},
{"learn":[0.5663498719],"iteration":983,"passed_time":12.15081361,"remaining_time":0.1975742051},
{"learn":[0.5662819428],"iteration":984,"passed_time":12.16209449,"remaining_time":0.1852095608},
{"learn":[0.5662160624],"iteration":985,"passed_time":12.17377703,"remaining_time":0.1728528179},
{"learn":[0.5661322813],"iteration":986,"passed_time":12.18645705,"remaining_time":0.1605105792},
{"learn":[0.5660583015],"iteration":987,"passed_time":12.1976184,"remaining_time":0.1481492113},
{"learn":[0.5659951616],"iteration":988,"passed_time":12.20961442,"remaining_time":0.1357995537},
{"learn":[0.5659062755],"iteration":989,"passed_time":12.22183596,"remaining_time":0.1234528885},
{"learn":[0.56584317],"iteration":990,"passed_time":12.23504307,"remaining_time":0.1111154264},
{"learn":[0.5657786504],"iteration":991,"passed_time":12.25327211,"remaining_time":0.09881671059},
{"learn":[0.5657388321],"iteration":992,"passed_time":12.27055361,"remaining_time":0.08649937087},
{"learn":[0.5656811805],"iteration":993,"passed_time":12.28816457,"remaining_time":0.0741740316},
{"learn":[0.5656130148],"iteration":994,"passed_time":12.30050588,"remaining_time":0.06181158732},
{"learn":[0.5655621882],"iteration":995,"passed_time":12.3117149,"remaining_time":0.04944463813},
{"learn":[0.5654541049],"iteration":996,"passed_time":12.32387663,"remaining_time":0.03708287851},
{"learn":[0.5653962586],"iteration":997,"passed_time":12.336227,"remaining_time":0.02472189779},
{"learn":[0.5653126132],"iteration":998,"passed_time":12.34729771,"remaining_time":0.01235965737},
{"learn":[0.565274582],"iteration":999,"passed_time":12.35944739,"remaining_time":0}
]}